{"data": [{"index": 1, "title": "碧生源 奥利司他胶囊 25粒 减肥减脂减重 1盒装", "ShopName": "碧生源大药房旗舰店", "DetailsUrl": "https://item.jd.com/10049791602558.html", "price": "67.80", "imgUrl": "https://img13.360buyimg.com/n7/jfs/t1/234116/19/18395/69734/66594720Faf6a55aa/359d436b237b25b5.jpg.avif", "统计信息": {"好评数": "500+", "好评率": "94%", "差评": "10+", "追评数": "4", "总评论数": "5000+", "评分统计": {"1星数": 16, "2星数": 5, "3星数": 8, "4星数": 28, "5星数": 500}, "商品信息": {"品牌信息": "碧生源", "商品名称": "碧生源 奥利司他胶囊 25粒 减肥减脂减重 排油减肥 1盒装", "商品编号": "10049791602558", "店铺": " 碧生源大药房旗舰店", "货号": "014080", "药品剂型": "胶囊剂", "类别": "西药", "适用人群": "成人", "使用方法": "口服", "国产/进口": "国产"}}}, {"index": 2, "title": "雅塑奥利司他胶囊减肥药18粒 奥利斯塔减肥药减脂减重奥利司他胶囊排油减肥抗肥胖油丸国药准字 1盒装 雅塑 奥利司他胶囊18粒/盒", "ShopName": "徍彧昇大药房旗舰店", "DetailsUrl": "https://item.jd.com/10087548419199.html", "price": "38.80", "imgUrl": "https://img14.360buyimg.com/n7/jfs/t1/128139/26/37512/93240/651fd729Fe1709062/4f24695bbadeddcb.png.avif", "统计信息": {"好评数": "3", "好评率": "100%", "差评": "0", "追评数": "0", "总评论数": "10", "评分统计": {"1星数": 0, "2星数": 0, "3星数": 0, "4星数": 0, "5星数": 3}, "商品信息": {"品牌信息": "雅塑", "商品名称": "雅塑奥利司他胶囊减肥药18粒 奥利斯塔减肥药减脂减重奥利司他胶囊排油减肥抗肥胖油丸国药准字 1盒装 雅塑 奥利司他胶囊18粒/盒", "商品编号": "10087548419199", "店铺": " 徍彧昇大药房旗舰店", "药品剂型": "胶囊剂", "类别": "非处方药，西药", "适用人群": "成人", "使用方法": "口服", "国产/进口": "国产"}}}, {"index": 3, "title": "减肥药 强效减肥药快顽固性肥胖瘦大肚子脂肪厚治肥胖症去除脂肪代谢不佳健康减脂 维生素B1片 1盒装#多盒效果好", "ShopName": "醉枫染墨大药房旗舰店", "DetailsUrl": "https://item.jd.com/10103756961345.html", "price": "6.80", "imgUrl": "https://img10.360buyimg.com/n7/jfs/t1/206422/17/36189/257792/66447425F2b4981ec/e3446295fe0eda7c.png.avif", "统计信息": {"好评数": "10+", "好评率": "100%", "差评": "0", "追评数": "0", "总评论数": "14", "评分统计": {"1星数": 0, "2星数": 0, "3星数": 0, "4星数": 0, "5星数": 11}, "商品信息": {"品牌信息": "玉威", "商品名称": "减肥药 强效减肥药快顽固性肥胖瘦大肚子脂肪厚治肥胖症去除脂肪代谢不佳健康减脂 维生素B1片 1盒装#多盒效果好", "商品编号": "10103756961345", "店铺": " 醉枫染墨大药房旗舰店", "适用人群": "儿童", "类别": "西药", "药品剂型": "片剂", "使用方法": "口服", "国产/进口": "国产"}}}, {"index": 4, "title": "治肥胖症强效减肥药快中药减肥药祛湿排毒去除湿气瘦大肚子去除脂肪湿气重顽固性肥胖调理中成药 苦胆草片 1盒【药房直发】", "ShopName": "柏丝卓洛阳大药房旗舰店", "DetailsUrl": "https://item.jd.com/10103759790885.html", "price": "12.50", "imgUrl": "https://img10.360buyimg.com/n7/jfs/t1/237245/17/16289/172657/66447997Fc012903a/3fa648c36105a31f.jpg.avif", "统计信息": {"好评数": "3", "好评率": "100%", "差评": "0", "追评数": "0", "总评论数": "6", "评分统计": {"1星数": 0, "2星数": 0, "3星数": 0, "4星数": 0, "5星数": 3}, "商品信息": {"品牌信息": "顺势", "商品名称": "治肥胖症强效减肥药快中药减肥药祛湿排毒去除湿气瘦大肚子去除脂肪湿气重顽固性肥胖调理中成药 苦胆草片 1盒【药房直发】", "商品编号": "10103759790885", "店铺": " 柏丝卓洛阳大药房旗舰店", "药品剂型": "片剂", "适用人群": "通用", "类别": "中成药", "使用方法": "口服", "国产/进口": "国产"}}}, {"index": 5, "title": "京东国际\n日本进口 皇汉堂小粉丸便秘药清肠便秘丸排油丸润肠通便调理肠道清宿便原装进口 小粉丸400粒/盒", "ShopName": "YOSHIKI海外专营店", "DetailsUrl": "https://item.jd.com/10041969710671.html", "price": "60.00", "imgUrl": "https://img11.360buyimg.com/n7/jfs/t1/174509/16/33206/115946/63dd18f5Fd985b31f/ea9fcdf85c2c1fe8.jpg.avif", "统计信息": {"好评数": "10", "好评率": "100%", "差评": "0", "追评数": "0", "总评论数": "100+", "评分统计": {"1星数": 0, "2星数": 0, "3星数": 0, "4星数": 0, "5星数": 10}, "商品信息": {"品牌信息": "皇汉堂（KOKANDO）", "商品名称": "日本进口 皇汉堂小粉丸便秘药清肠便秘丸排油丸润肠通便调理肠道清宿便减肥药原装进口 小粉丸400粒/盒", "商品编号": "10041969710671", "店铺": " YOSHIKI海外专营店", "适用症状": "便秘", "适用人群": "通用", "使用方法": "口服", "药品类型": "西药"}}}, {"index": 6, "title": "治肥胖症中药减肥药强效减肥药快肚子大湿气重湿气大肚子肥胖体重超标减不下去肥祛湿排毒专用 防风通圣丸 3盒【肚子变小了 减重超快】", "ShopName": "花丛懒大药房旗舰店", "DetailsUrl": "https://item.jd.com/10105579551082.html", "price": "29.90", "imgUrl": "https://img12.360buyimg.com/n7/jfs/t1/228675/14/19052/128367/665d6b6bFcf4fd56d/d65ffc54447c7a4c.jpg.avif", "统计信息": {"好评数": "0", "好评率": "100%", "差评": "0", "追评数": "0", "总评论数": "0", "评分统计": {"1星数": 0, "2星数": 0, "3星数": 0, "4星数": 0, "5星数": 0}, "商品信息": {"品牌信息": "立效", "商品名称": "治肥胖症中药减肥药强效减肥药快肚子大湿气重湿气大肚子肥胖体重超标减不下去肥祛湿排毒专用药 防风通圣丸 3盒【肚子变小了 减重超快】", "商品编号": "10105579551082", "店铺": " 花丛懒大药房旗舰店", "货号": "张廷玉", "国产/进口": "国产", "药品剂型": "丸剂"}}}, {"index": 7, "title": "宝元堂 便秘果肉250克【精选肉厚去壳】便秘果仁随便果大解果", "ShopName": "宝元堂（BAOYUANTANG）京东自营旗舰店", "DetailsUrl": "https://item.jd.com/100078402529.html", "price": "37.40", "imgUrl": "https://img14.360buyimg.com/n7/jfs/t1/224750/8/10234/86391/658cd279Fbca821a1/963e5fcef9b49c12.jpg.avif", "统计信息": {"好评数": "1万+", "好评率": "96%", "差评": "100+", "追评数": "50+", "总评论数": "5万+", "评分统计": {"1星数": 100, "2星数": 66, "3星数": 100, "4星数": 200, "5星数": 10000}, "商品信息": {"品牌信息": "宝元堂（BAOYUANTANG）", "商品名称": "宝元堂便秘果肉250克", "商品编号": "100078402529", "包装形式": "袋装", "类别": "其他", "国产/进口": "国产"}}}, {"index": 8, "title": "治严重肥胖症减肥药顽固性肥胖瘦肚子脂肪瘦身排油去除多余脂肪湿气重去湿气肚子大排毒燃脂中药 龙胆泻肝片 一盒（多盒效更佳）", "ShopName": "尚莱萱洛阳大药房旗舰店", "DetailsUrl": "https://item.jd.com/10102724789835.html", "price": "15.50", "imgUrl": "https://img10.360buyimg.com/n7/jfs/t1/134266/16/41892/129836/6635d3d0Ff84ce3ea/8d0ebce349fe7140.jpg.avif", "统计信息": {"好评数": "2", "好评率": "100%", "差评": "0", "追评数": "0", "总评论数": "2", "评分统计": {"1星数": 0, "2星数": 0, "3星数": 0, "4星数": 0, "5星数": 2}, "商品信息": {"品牌信息": "愉泰", "商品名称": "治严重肥胖症减肥药顽固性肥胖瘦肚子脂肪瘦身排油去除多余脂肪湿气重去湿气肚子大排毒燃脂中药 龙胆泻肝片 一盒（多盒效更佳）", "商品编号": "10102724789835", "店铺": " 尚莱萱洛阳大药房旗舰店", "药品剂型": "片剂", "类别": "中成药", "适用人群": "成人", "使用方法": "口服", "国产/进口": "国产"}}}, {"index": 9, "title": "仁和奥利司他胶囊60mg*18粒排油减肥国药准字减肚子减肥药非快瘦肚子 1盒艾-丽 1盒艾-丽 奥利司他胶囊60mg*18粒", "ShopName": "长沙捌零玖零大药房旗舰店", "DetailsUrl": "https://item.jd.com/10102838278295.html", "price": "37.24", "imgUrl": "https://img10.360buyimg.com/n7/jfs/t1/193656/8/44186/113276/663795a0Fa7273054/9da431127f2dee2f.jpg.avif", "统计信息": {"好评数": "0", "好评率": "100%", "差评": "0", "追评数": "0", "总评论数": "3", "评分统计": {"1星数": 0, "2星数": 0, "3星数": 0, "4星数": 0, "5星数": 0}, "商品信息": {"品牌信息": "未知", "商品名称": "仁和奥利司他胶囊60mg*18粒排油减肥国药准字减肚子减肥药非快瘦肚子 1盒艾-丽 1盒艾-丽 奥利司他胶囊60mg*18粒", "商品编号": "10102838278295", "店铺": " 长沙捌零玖零大药房旗舰店", "货号": "35190", "类别": "西药", "药品剂型": "胶囊剂", "适用人群": "成人", "使用方法": "口服", "国产/进口": "国产"}}}, {"index": 10, "title": "治肥胖症减肥药】减肥瘦肚子燃脂中药减肥全身瘦大肚子肥胖脂肪多湿气重健脾胃排油专用 参苓白术散 2盒装【加快脂肪代谢】", "ShopName": "梦尚丽大药房旗舰店", "DetailsUrl": "https://item.jd.com/10105575692857.html", "price": "44.38", "imgUrl": "https://img12.360buyimg.com/n7/jfs/t1/163133/19/26613/67584/665d6701Fdbf2d76d/6e9973623ad956b3.png.avif", "统计信息": {"好评数": "0", "好评率": "100%", "差评": "0", "追评数": "0", "总评论数": "0", "评分统计": {"1星数": 0, "2星数": 0, "3星数": 0, "4星数": 0, "5星数": 0}, "商品信息": {"品牌信息": "立效", "商品名称": "治肥胖症减肥药】减肥瘦肚子燃脂中药减肥全身瘦大肚子肥胖脂肪多湿气重健脾胃排油专用药 参苓白术散 2盒装【加快脂肪代谢】", "商品编号": "10105575692857", "店铺": " 梦尚丽大药房旗舰店", "货号": "郜毅", "适用人群": "通用", "类别": "中成药", "药品剂型": "散剂", "使用方法": "口服", "国产/进口": "国产"}}}, {"index": 11, "title": "治肥胖症减肥药】减肥瘦肚子燃脂中药减肥强傚快不节食不运动祛湿排毒去除湿气瘦肚子中成药 龙胆泻肝片 3盒装【轻松享瘦】", "ShopName": "视星球洛阳大药房旗舰店", "DetailsUrl": "https://item.jd.com/10101792534646.html", "price": "47.40", "imgUrl": "https://img11.360buyimg.com/n7/jfs/t1/156860/9/44031/75087/66272e31Fe9df9fb4/9b2d5b235e30bdb3.jpg.avif", "统计信息": {"好评数": "10+", "好评率": "100%", "差评": "0", "追评数": "4", "总评论数": "28", "评分统计": {"1星数": 0, "2星数": 0, "3星数": 0, "4星数": 0, "5星数": 19}, "商品信息": {"品牌信息": "愉泰", "商品名称": "治肥胖症减肥药】减肥瘦肚子燃脂中药减肥强傚快不节食不运动祛湿排毒去除湿气瘦肚子中成药 龙胆泻肝片 3盒装【轻松享瘦】", "商品编号": "10101792534646", "店铺": " 视星球洛阳大药房旗舰店", "货号": "ws", "适用人群": "儿童", "类别": "中成药", "药品剂型": "片剂", "使用方法": "口服", "国产/进口": "国产"}}}, {"index": 12, "title": "治肥胖症减肥药】减肥瘦肚子燃脂中药减肥全身瘦大肚子肥胖脂肪多湿气重健脾胃排油专用 参苓白术散 3盒装【喝水都长胖】", "ShopName": "梦尚丽大药房旗舰店", "DetailsUrl": "https://item.jd.com/10105575692858.html", "price": "65.20", "imgUrl": "https://img13.360buyimg.com/n7/jfs/t1/163133/19/26613/67584/665d6701Fdbf2d76d/6e9973623ad956b3.png.avif", "统计信息": {"好评数": "0", "好评率": "100%", "差评": "0", "追评数": "0", "总评论数": "0", "评分统计": {"1星数": 0, "2星数": 0, "3星数": 0, "4星数": 0, "5星数": 0}, "商品信息": {"品牌信息": "立效", "商品名称": "治肥胖症减肥药】减肥瘦肚子燃脂中药减肥全身瘦大肚子肥胖脂肪多湿气重健脾胃排油专用药 参苓白术散 3盒装【喝水都长胖】", "商品编号": "10105575692858", "店铺": " 梦尚丽大药房旗舰店", "货号": "郜毅", "适用人群": "通用", "类别": "中成药", "药品剂型": "散剂", "使用方法": "口服", "国产/进口": "国产"}}}, {"index": 13, "title": "【品牌直供】德国原装进口HEXAL奥利司他排油丸胶囊84粒 1盒装【2024年10月】", "ShopName": "AWDLOG海外卖场店", "DetailsUrl": "https://item.jd.com/10029080386358.html", "price": "188.00", "imgUrl": "https://img13.360buyimg.com/n7/jfs/t1/170915/27/24373/191085/6152bff7Ee3a858a1/69fe96cacd4f2f3b.jpg.avif", "统计信息": {"好评数": "1200+", "好评率": "97%", "差评": "20+", "追评数": "40+", "总评论数": "5000+", "评分统计": {"1星数": 24, "2星数": 2, "3星数": 11, "4星数": 9, "5星数": 1000}, "商品信息": {"品牌信息": "HEXAL", "商品名称": "【品牌直供】德国原装进口HEXAL奥利司他排油丸胶囊84粒 1盒装【2024年10月】", "商品编号": "10029080386358", "店铺": " AWDLOG海外卖场店", "适用症状": "便秘", "适用人群": "通用", "使用方法": "口服", "药品类型": "西药"}}}, {"index": 14, "title": "雅塑奥利司他胶囊排油减肥正i品国药准字减肥中药快瘦肚子强I效减肥药快不节食不运动反弹快女瘦身 5盒【大多数人的选择】", "ShopName": "仁美仁舒大药房旗舰店", "DetailsUrl": "https://item.jd.com/10102963966421.html", "price": "48.00", "imgUrl": "https://img11.360buyimg.com/n7/jfs/t1/171667/12/46212/61587/6639a916F2da9c841/43ef0cbef0d0c23c.jpg.avif", "统计信息": {"好评数": "0", "好评率": "100%", "差评": "0", "追评数": "0", "总评论数": "1", "评分统计": {"1星数": 0, "2星数": 0, "3星数": 0, "4星数": 0, "5星数": 0}, "商品信息": {"品牌信息": "雅塑", "商品名称": "雅塑奥利司他胶囊排油减肥正i品国药准字减肥中药快瘦肚子强I效减肥药快不节食不运动反弹减肥快女瘦身减肥 5盒【大多数人的选择】", "商品编号": "10102963966421", "店铺": " 仁美仁舒大药房旗舰店", "类别": "西药", "药品剂型": "胶囊剂", "适用人群": "成人", "使用方法": "口服", "国产/进口": "国产"}}}, {"index": 15, "title": "治肥胖症中药减肥药强效减肥药快肚子大湿气重湿气大肚子肥胖体重超标减不下去肥祛湿排毒专用 防风通圣丸 防风通圣丸*2+奥利司他*2【懒人", "ShopName": "花丛懒大药房旗舰店", "DetailsUrl": "https://item.jd.com/10105579551086.html", "price": "61.50", "imgUrl": "https://img11.360buyimg.com/n7/jfs/t1/174549/14/46386/111031/665d6b6aF3284012b/7c243485c6883438.jpg.avif", "统计信息": {"好评数": "0", "好评率": "100%", "差评": "0", "追评数": "0", "总评论数": "0", "评分统计": {"1星数": 0, "2星数": 0, "3星数": 0, "4星数": 0, "5星数": 0}, "商品信息": {"品牌信息": "立效", "商品名称": "治肥胖症中药减肥药强效减肥药快肚子大湿气重湿气大肚子肥胖体重超标减不下去肥祛湿排毒专用药 防风通圣丸 防风通圣丸*2+奥利司他*2【懒人减肥专属】", "商品编号": "10105579551086", "店铺": " 花丛懒大药房旗舰店", "货号": "张廷玉", "国产/进口": "国产", "药品剂型": "丸剂"}}}, {"index": 16, "title": "减肥药 强傚减肥药快女抑制食欲不节食不运动肥胖症药 奥利司他胶囊 减脂肪瘦肚子燃脂男女士排油用药 1盒", "ShopName": "秀亦熙洛阳大药房旗舰店", "DetailsUrl": "https://item.jd.com/10102428623617.html", "price": "19.80", "imgUrl": "https://img12.360buyimg.com/n7/jfs/t1/238127/23/15062/105415/66305531F9ac33575/8d069cbd3add21bc.jpg.avif", "统计信息": {"好评数": "4", "好评率": "100%", "差评": "0", "追评数": "0", "总评论数": "4", "评分统计": {"1星数": 0, "2星数": 0, "3星数": 0, "4星数": 0, "5星数": 4}, "商品信息": {"品牌信息": "雅塑", "商品名称": "减肥药 强傚减肥药快女抑制食欲不节食不运动肥胖症药 奥利司他胶囊 减脂肪瘦肚子减肥燃脂男女士排油用药 1盒", "商品编号": "10102428623617", "店铺": " 秀亦熙洛阳大药房旗舰店", "药品剂型": "胶囊剂", "适用人群": "成人", "类别": "西药", "使用方法": "口服", "国产/进口": "国产"}}}, {"index": 17, "title": "提高脂肪代谢药减肥药促进新陈代谢燃烧脂肪塑造完美身材增强饱腹感胃肠道蠕动帮助消化 复合维生素B片 1盒装【去湿气】基础装", "ShopName": "牧味初大药房旗舰店", "DetailsUrl": "https://item.jd.com/10104641816656.html", "price": "11.30", "imgUrl": "https://img11.360buyimg.com/n7/jfs/t1/123052/1/42938/127255/665002a7F8844af60/bc358509cd245064.jpg.avif", "统计信息": {"好评数": "0", "好评率": "100%", "差评": "0", "追评数": "0", "总评论数": "0", "评分统计": {"1星数": 0, "2星数": 0, "3星数": 0, "4星数": 0, "5星数": 0}, "商品信息": {"品牌信息": "南岛", "商品名称": "提高脂肪代谢药减肥药促进新陈代谢燃烧脂肪塑造完美身材增强饱腹感胃肠道蠕动帮助消化 复合维生素B片 1盒装【去湿气】基础装", "商品编号": "10104641816656", "店铺": " 牧味初大药房旗舰店", "类别": "西药", "国产/进口": "国产", "适用人群": "通用", "药品剂型": "片剂", "使用方法": "口服", "适用症状": "食欲缺乏，厌食"}}}, {"index": 18, "title": "治肥胖症强效減肥药快中药减肥药祛湿排毒去除湿气瘦大肚子去除脂肪湿气重顽固性肥胖调理中成药龙胆泻肝片 一盒装【建议多盒服用】", "ShopName": "埃拉锶大药房旗舰店", "DetailsUrl": "https://item.jd.com/10105492548870.html", "price": "15.90", "imgUrl": "https://img10.360buyimg.com/n7/jfs/t1/206925/14/42382/108129/665c2612F2e34209e/413b2e35e264bcf5.jpg.avif", "统计信息": {"好评数": "0", "好评率": "100%", "差评": "0", "追评数": "0", "总评论数": "0", "评分统计": {"1星数": 0, "2星数": 0, "3星数": 0, "4星数": 0, "5星数": 0}, "商品信息": {"品牌信息": "愉泰", "商品名称": "治肥胖症强效減肥药快中药减肥药祛湿排毒去除湿气瘦大肚子去除脂肪湿气重顽固性肥胖调理中成药龙胆泻肝片 一盒装【建议多盒服用】", "商品编号": "10105492548870", "店铺": " 埃拉锶大药房旗舰店", "药品剂型": "片剂", "类别": "中成药", "适用人群": "儿童", "使用方法": "口服", "国产/进口": "国产"}}}, {"index": 19, "title": "999玖减奥利司他胶囊 成人抗肥胖排油减脂减重减肥药", "ShopName": "惠宝稔明大药房旗舰店", "DetailsUrl": "https://item.jd.com/10082664224501.html", "price": "75.00", "imgUrl": "https://img11.360buyimg.com/n7/jfs/t1/181596/2/35995/134017/64d0b808Fba18768d/1bae6a09a3d5a743.jpg.avif", "统计信息": {"好评数": "5", "好评率": "83%", "差评": "1", "追评数": "0", "总评论数": "47", "评分统计": {"1星数": 1, "2星数": 0, "3星数": 0, "4星数": 0, "5星数": 5}, "商品信息": {"品牌信息": "999", "商品名称": "999玖减奥利司他胶囊60mg*5粒 成人抗肥胖、排油减脂、减重减肥药 3盒奥利司他胶*5粒【可服用5天】", "商品编号": "10082664224501", "店铺": " 惠宝稔明大药房旗舰店", "货号": "8013319", "适用人群": "成人", "药品剂型": "胶囊剂", "类别": "西药", "使用方法": "口服", "国产/进口": "国产"}}}, {"index": 20, "title": "减肥胖症中药减肥药祛湿排毒去除湿气瘦肚子不节食不运动男女强效减肥药快燃脂减脂 逍遥丸 1盒装/轻度肥胖", "ShopName": "赞译洛阳大药房旗舰店", "DetailsUrl": "https://item.jd.com/10103291658628.html", "price": "13.75", "imgUrl": "https://img13.360buyimg.com/n7/jfs/t1/196890/3/43803/454858/663de25dFbf71fda9/b6a823d94f72964f.png.avif", "统计信息": {"好评数": "6", "好评率": "100%", "差评": "0", "追评数": "0", "总评论数": "7", "评分统计": {"1星数": 0, "2星数": 0, "3星数": 0, "4星数": 0, "5星数": 6}, "商品信息": {"品牌信息": "梁湖（LIANG HU）", "商品名称": "减肥胖症中药减肥药祛湿排毒去除湿气瘦肚子不节食不运动男女强效减肥药快燃脂减脂 逍遥丸 1盒装/轻度肥胖", "商品编号": "10103291658628", "店铺": " 赞译洛阳大药房旗舰店", "国产/进口": "国产", "药品剂型": "丸剂"}}}, {"index": 21, "title": "中药减肥药 强效 强效减肥药快 减肥瘦肚子燃脂 防风通圣丸减肥药强效效减肥药 中药全身瘦正品 3盒*男女通用超猛", "ShopName": "牧味初洛阳大药房旗舰店", "DetailsUrl": "https://item.jd.com/10105493943765.html", "price": "29.80", "imgUrl": "https://img10.360buyimg.com/n7/jfs/t1/247397/39/9774/96050/665c297bF90fda83b/657b8e8f8d4c7d54.jpg.avif", "统计信息": {"好评数": "0", "好评率": "100%", "差评": "0", "追评数": "0", "总评论数": "0", "评分统计": {"1星数": 0, "2星数": 0, "3星数": 0, "4星数": 0, "5星数": 0}, "商品信息": {"品牌信息": "立效", "商品名称": "中药减肥药 强效 强效减肥药快  减肥瘦肚子燃脂  防风通圣丸减肥药强效效减肥药 中药减肥全身瘦正品 3盒*男女通用减肥超猛", "商品编号": "10105493943765", "店铺": " 牧味初洛阳大药房旗舰店", "货号": "123", "类别": "中成药", "适用症状": "便秘", "药品剂型": "丸剂", "适用人群": "成人", "使用方法": "口服", "国产/进口": "国产"}}}, {"index": 22, "title": "减肥药 强效减肥药快减肥瘦肚子燃脂减肥产品正不品反弹女性快速减肥排油减脂瘦肚子瘦腿瘦全身奥利司他胶囊 1盒装", "ShopName": "璀冠洛阳大药房旗舰店", "DetailsUrl": "https://item.jd.com/10105408169963.html", "price": "19.80", "imgUrl": "https://img13.360buyimg.com/n7/jfs/t1/217495/18/42849/78530/665aca0eF467e8f03/ca2b8214b571e089.jpg.avif", "统计信息": {"好评数": "0", "好评率": "100%", "差评": "0", "追评数": "0", "总评论数": "0", "评分统计": {"1星数": 0, "2星数": 0, "3星数": 0, "4星数": 0, "5星数": 0}, "商品信息": {"品牌信息": "雅塑", "商品名称": "减肥药 强效减肥药快减肥瘦肚子燃脂减肥产品正不品反弹女性快速减肥排油减脂瘦肚子瘦腿瘦全身奥利司他胶囊 1盒装", "商品编号": "10105408169963", "店铺": " 璀冠洛阳大药房旗舰店", "类别": "西药", "适用人群": "成人", "药品剂型": "胶囊剂", "使用方法": "口服", "国产/进口": "国产"}}}, {"index": 23, "title": "碧生源奥利司他胶囊排油减肥真品国药准字25粒减肚子排油减脂瘦身傚七斤寿排油塑身瘦肚子 5盒装【碧生源25粒/盒】", "ShopName": "正和心安大药房旗舰店", "DetailsUrl": "https://item.jd.com/10103991739306.html", "price": "430.80", "imgUrl": "https://img11.360buyimg.com/n7/jfs/t1/154802/10/38545/160910/66475d53F9a566291/eed00ea3cab4ae00.jpg.avif", "统计信息": {"好评数": "0", "好评率": "100%", "差评": "0", "追评数": "0", "总评论数": "0", "评分统计": {"1星数": 0, "2星数": 0, "3星数": 0, "4星数": 0, "5星数": 0}, "商品信息": {"品牌信息": "碧生源", "商品名称": "碧生源奥利司他胶囊排油减肥真品国药准字25粒减肚子排油减脂瘦身傚七斤寿排油减肥药减肥塑身瘦肚子 5盒装【碧生源25粒/盒】", "商品编号": "10103991739306", "店铺": " 正和心安大药房旗舰店", "货号": "SP8490", "适用人群": "成人", "类别": "西药", "药品剂型": "胶囊剂", "使用方法": "口服", "国产/进口": "国产"}}}, {"index": 24, "title": "[雅塑] 奥利司他胶囊 0.12g*18粒/盒体重超重患者 1盒", "ShopName": "四方百信大药房旗舰店", "DetailsUrl": "https://item.jd.com/10098686397157.html", "price": "29.90", "imgUrl": "https://img12.360buyimg.com/n7/jfs/t1/209506/11/40724/697284/65f935b8Fd2298354/b928e4f704f46623.png.avif", "统计信息": {"好评数": "10+", "好评率": "85%", "差评": "0", "追评数": "0", "总评论数": "100+", "评分统计": {"1星数": 0, "2星数": 1, "3星数": 1, "4星数": 3, "5星数": 9}, "商品信息": {"品牌信息": "雅塑", "商品名称": "[雅塑] 奥利司他胶囊 0.12g*18粒/盒体重超重患者 1盒", "商品编号": "10098686397157", "店铺": " 四方百信大药房旗舰店", "货号": "1240301014", "类别": "西药", "药品剂型": "胶囊剂", "适用人群": "成人", "使用方法": "口服", "国产/进口": "国产"}}}, {"index": 25, "title": "伟博天然webber naturals 复合膳食纤维胶囊PGX饱腹节食代餐赘肉控制加拿大原装进口 150粒装", "ShopName": "webber naturals海外旗舰店", "DetailsUrl": "https://item.jd.com/1970220609.html", "price": "328.00", "imgUrl": "https://img14.360buyimg.com/n7/jfs/t1/199039/33/12935/124771/61668572E587e4365/2f5e1ba16b33756d.jpg.avif", "统计信息": {"好评数": "200+", "好评率": "97%", "差评": "3", "追评数": "3", "总评论数": "200+", "评分统计": {"1星数": 3, "2星数": 0, "3星数": 2, "4星数": 0, "5星数": 71}, "商品信息": {"品牌信息": "Webber Naturals", "商品名称": "伟博天然webber naturals 复合膳食纤维胶囊PGX饱腹节食代餐赘肉控制加拿大原装进口 150粒装", "商品编号": "1970220609", "店铺": " webber naturals海外旗舰店", "货号": "625273037517", "是否保健食品": "营养膳食补充剂（非食健字）", "类别": "固体饮料", "剂型": "胶囊", "包装形式": "瓶装", "国产/进口": "进口"}}}, {"index": 26, "title": "京东国际\nOrlistat HEXAL德国奥利司他胶囊84粒 减肥药减脂瘦身排油丸减重进口Orlistat", "ShopName": "京东健康国际自营药房", "DetailsUrl": "https://item.jd.com/100013891108.html", "price": "193.00", "imgUrl": "https://img13.360buyimg.com/n7/jfs/t1/173844/3/45353/99694/6656e444F8995ecce/5efc77d06dff0917.jpg.avif", "统计信息": {"好评数": "1万+", "好评率": "96%", "差评": "200+", "追评数": "100+", "总评论数": "5万+", "评分统计": {"1星数": 200, "2星数": 67, "3星数": 100, "4星数": 100, "5星数": 10000}, "商品信息": {"品牌信息": "Orlistat HEXAL", "商品名称": "Orlistat HEXAL奥利司他胶囊排油丸84粒/盒", "商品编号": "100013891108", "药品类型": "西药", "适用人群": "通用", "使用方法": "口服", "适用症状": "便秘"}}}, {"index": 27, "title": "赛乐赛 奥利司他胶囊 排油减肥减肥药强傚效减肥药快男女瘦腿减脂肪减肥瘦肚子减重瘦身 3盒装【艾/丽-6粒】减脂减重", "ShopName": "黛参苓大药房官方旗舰店", "DetailsUrl": "https://item.jd.com/10102054700232.html", "price": "39.00", "imgUrl": "https://img12.360buyimg.com/n7/jfs/t1/173097/36/43624/58450/663070dcF24937e70/10060d8fd3296abd.jpg.avif", "统计信息": {"好评数": "10+", "好评率": "86%", "差评": "0", "追评数": "0", "总评论数": "200+", "评分统计": {"1星数": 0, "2星数": 2, "3星数": 0, "4星数": 3, "5星数": 10}, "商品信息": {"品牌信息": "赛乐赛", "商品名称": "赛乐赛 奥利司他胶囊 排油减肥减肥药强傚效减肥药快男女瘦腿减脂肪减肥瘦肚子减重瘦身 3盒装【艾/丽-6粒】减脂减重", "商品编号": "10102054700232", "店铺": " 黛参苓大药房官方旗舰店", "适用人群": "成人", "类别": "西药", "药品剂型": "胶囊剂", "使用方法": "口服", "国产/进口": "国产"}}}, {"index": 28, "title": "减肥药强效减肥药快女不节食不运动肥胖症药体重超重减脂肪瘦肚子瘦肚子减手臂效赛乐赛排油奥利司他胶囊 3盒【大肚腩消失了】", "ShopName": "濯乐泉大药房旗舰店", "DetailsUrl": "https://item.jd.com/10089996190970.html", "price": "53.00", "imgUrl": "https://img10.360buyimg.com/n7/jfs/t1/88141/4/46583/95507/664f052bF34174f34/d73de1cf97132332.jpg.avif", "统计信息": {"好评数": "50+", "好评率": "84%", "差评": "7", "追评数": "2", "总评论数": "200+", "评分统计": {"1星数": 7, "2星数": 0, "3星数": 3, "4星数": 1, "5星数": 53}, "商品信息": {"品牌信息": "雅塑", "商品名称": "减肥药强效减肥药快女不节食不运动肥胖症药体重超重减脂肪瘦肚子瘦肚子减手臂效赛乐赛排油奥利司他胶囊 3盒【大肚腩消失了】", "商品编号": "10089996190970", "店铺": " 濯乐泉大药房旗舰店", "适用人群": "成人", "药品剂型": "胶囊剂", "类别": "西药", "使用方法": "口服", "国产/进口": "国产"}}}, {"index": 29, "title": "舒尔佳 奥利司他胶囊 减脂减重 减肥药 塑身排油 排油丸 治疗肥胖0.12g7粒装 7粒*1盒", "ShopName": "鲁南官方旗舰店", "DetailsUrl": "https://item.jd.com/48451806194.html", "price": "58.90", "imgUrl": "https://img14.360buyimg.com/n7/jfs/t1/237490/21/13661/85610/65eb233fF56c7adbd/f100a7e76ec9b12a.jpg.avif", "统计信息": {"好评数": "1800+", "好评率": "97%", "差评": "20+", "追评数": "20+", "总评论数": "1万+", "评分统计": {"1星数": 20, "2星数": 8, "3星数": 21, "4星数": 25, "5星数": 1000}, "商品信息": {"品牌信息": "舒尔佳", "商品名称": "舒尔佳 奥利司他胶囊 减脂减重 减肥药 塑身排油 排油丸 治疗肥胖0.12g7粒装 7粒*1盒", "商品编号": "48451806194", "店铺": " 鲁南官方旗舰店", "货号": "BOF005031C", "药品剂型": "胶囊剂", "适用人群": "成人", "类别": "西药", "使用方法": "口服", "国产/进口": "国产"}}}, {"index": 30, "title": "[雅塑] 奥利司他胶囊 0.12g*18粒/盒 1盒装【央企连锁 药房直发】", "ShopName": "国药控股扬州大药房旗舰店", "DetailsUrl": "https://item.jd.com/10104461856902.html", "price": "29.80", "imgUrl": "https://img12.360buyimg.com/n7/jfs/t1/151369/12/38263/117328/665569daF53b5fd3f/c9db6042ef1ea168.jpg.avif", "统计信息": {"好评数": "0", "好评率": "100%", "差评": "0", "追评数": "0", "总评论数": "1", "评分统计": {"1星数": 0, "2星数": 0, "3星数": 0, "4星数": 0, "5星数": 0}, "商品信息": {"品牌信息": "雅塑", "商品名称": "[雅塑] 奥利司他胶囊 0.12g*18粒/盒 1盒装【央企连锁 药房直发】", "商品编号": "10104461856902", "店铺": " 国药控股扬州大药房旗舰店", "货号": "XEH6000301", "药品剂型": "胶囊剂", "国产/进口": "国产"}}}, {"index": 31, "title": "伟博天然webber naturals 复合膳食纤维胶囊PGX饱腹节食代餐赘肉控制加拿大原装进口 150粒装", "ShopName": "webber naturals海外旗舰店", "DetailsUrl": "https://item.jd.com/1970220609.html", "price": "328.00", "imgUrl": "https://img14.360buyimg.com/n7/jfs/t1/199039/33/12935/124771/61668572E587e4365/2f5e1ba16b33756d.jpg.avif", "统计信息": {"好评数": "200+", "好评率": "97%", "差评": "3", "追评数": "3", "总评论数": "200+", "评分统计": {"1星数": 3, "2星数": 0, "3星数": 2, "4星数": 0, "5星数": 71}, "商品信息": {"品牌信息": "Webber Naturals", "商品名称": "伟博天然webber naturals 复合膳食纤维胶囊PGX饱腹节食代餐赘肉控制加拿大原装进口 150粒装", "商品编号": "1970220609", "店铺": " webber naturals海外旗舰店", "货号": "625273037517", "是否保健食品": "营养膳食补充剂（非食健字）", "类别": "固体饮料", "剂型": "胶囊", "包装形式": "瓶装", "国产/进口": "进口"}}}, {"index": 32, "title": "刘畊宏推荐】瘦大肚腩减赘肉肚子大减肥药治顽固肥胖症药促进脂肪代谢中药减肥 新效期 维生素B1片 1盒【基础装】不推荐", "ShopName": "墨如烟大药房旗舰店", "DetailsUrl": "https://item.jd.com/10097680472672.html", "price": "9.76", "imgUrl": "https://img12.360buyimg.com/n7/jfs/t1/232288/29/17827/132114/66514347Ffa8eb796/c06d6c0c7058f4eb.jpg.avif", "统计信息": {"好评数": "10+", "好评率": "100%", "差评": "0", "追评数": "0", "总评论数": "36", "评分统计": {"1星数": 0, "2星数": 0, "3星数": 0, "4星数": 0, "5星数": 15}, "商品信息": {"品牌信息": "玉威", "商品名称": "刘畊宏推荐】瘦大肚腩减赘肉肚子大减肥药治顽固肥胖症药促进脂肪代谢中药减肥 新效期 维生素B1片 1盒【基础装】不推荐", "商品编号": "10097680472672", "店铺": " 墨如烟大药房旗舰店", "货号": "kjn", "药品剂型": "片剂", "适用人群": "儿童", "类别": "西药", "使用方法": "口服", "国产/进口": "国产"}}}, {"index": 33, "title": "减肥药强效减肥药快中药减肥药不节食不运动 瘦肚子不i反弹燃烧脂肪减肥产品女性防风通圣丸 1盒装丿效果不明显", "ShopName": "洁嫣南大药房旗舰店", "DetailsUrl": "https://item.jd.com/10103649219319.html", "price": "10.80", "imgUrl": "https://img14.360buyimg.com/n7/jfs/t1/183985/38/45012/229899/6642db00F5d8baa6e/5cef065488c52d2c.png.avif", "统计信息": {"好评数": "3", "好评率": "100%", "差评": "0", "追评数": "0", "总评论数": "5", "评分统计": {"1星数": 0, "2星数": 0, "3星数": 0, "4星数": 0, "5星数": 3}, "商品信息": {"品牌信息": "立效", "商品名称": "减肥药强效减肥药快中药减肥药不节食不运动 瘦肚子不i反弹燃烧脂肪减肥产品女性减肥防风通圣丸 1盒装丿效果不明显", "商品编号": "10103649219319", "店铺": " 洁嫣南大药房旗舰店", "类别": "中成药", "适用症状": "便秘", "适用人群": "成人", "药品剂型": "丸剂", "使用方法": "口服", "国产/进口": "国产"}}}, {"index": 34, "title": "治肥胖症强效減肥药快中药减肥药祛湿排毒去除湿气瘦大肚子去除脂肪湿气重顽固性肥胖调理中成药归脾丸 组合装【归脾丸*1+奥利司他胶囊*1】", "ShopName": "梦尚丽洛阳大药房旗舰店", "DetailsUrl": "https://item.jd.com/10105488364364.html", "price": "32.80", "imgUrl": "https://img14.360buyimg.com/n7/jfs/t1/172836/9/46158/135870/665c1ad5F87706a4d/2d74023921edbe78.png.avif", "统计信息": {"好评数": "0", "好评率": "100%", "差评": "0", "追评数": "0", "总评论数": "0", "评分统计": {"1星数": 0, "2星数": 0, "3星数": 0, "4星数": 0, "5星数": 0}, "商品信息": {"品牌信息": "瑞华", "商品名称": "治肥胖症强效減肥药快中药减肥药祛湿排毒去除湿气瘦大肚子去除脂肪湿气重顽固性肥胖调理中成药归脾丸 组合装【归脾丸*1+奥利司他胶囊*1】", "商品编号": "10105488364364", "店铺": " 梦尚丽洛阳大药房旗舰店", "类别": "中成药", "适用人群": "通用", "药品剂型": "丸剂", "使用方法": "口服", "国产/进口": "国产"}}}, {"index": 35, "title": "肚子大湿气重】用于脾胃虚弱湿气重引起虚胖肚大脂肪堆积 参苓白术散可搭保济药丸奥利i司他 3盒装【脾胃虚弱肚子大】", "ShopName": "洛骆堂旗舰店", "DetailsUrl": "https://item.jd.com/10082069438797.html", "price": "65.00", "imgUrl": "https://img12.360buyimg.com/n7/jfs/t1/133053/11/38745/104936/65ebc0a2Fecd43225/c330be0dc4c536dd.jpg.avif", "统计信息": {"好评数": "10", "好评率": "100%", "差评": "0", "追评数": "0", "总评论数": "40", "评分统计": {"1星数": 0, "2星数": 0, "3星数": 0, "4星数": 0, "5星数": 10}, "商品信息": {"品牌信息": "克极", "商品名称": "肚子大湿气重】用于脾胃虚弱湿气重引起虚胖肚大脂肪堆积 参苓白术散可搭保济药丸奥利i司他减肥药 3盒装【脾胃虚弱肚子大】", "商品编号": "10082069438797", "店铺": " 洛骆堂旗舰店", "货号": "XY", "药品剂型": "散剂", "类别": "中成药", "适用人群": "通用", "使用方法": "口服", "国产/进口": "国产"}}}, {"index": 36, "title": "减肥药 强效减肥药快减肥瘦肚子燃脂减肥产品正不品反弹女性快速减肥排油减脂瘦肚子瘦腿瘦全身奥利司他胶囊 10盒装【拒绝反弹】", "ShopName": "璀冠洛阳大药房旗舰店", "DetailsUrl": "https://item.jd.com/10105408169966.html", "price": "151.47", "imgUrl": null, "统计信息": {"好评数": "0", "好评率": "100%", "差评": "0", "追评数": "0", "总评论数": "0", "评分统计": {"1星数": 0, "2星数": 0, "3星数": 0, "4星数": 0, "5星数": 0}, "商品信息": {"品牌信息": "雅塑", "商品名称": "减肥药 强效减肥药快减肥瘦肚子燃脂减肥产品正不品反弹女性快速减肥排油减脂瘦肚子瘦腿瘦全身奥利司他胶囊 10盒装【拒绝反弹】", "商品编号": "10105408169966", "店铺": " 璀冠洛阳大药房旗舰店", "类别": "西药", "适用人群": "成人", "药品剂型": "胶囊剂", "使用方法": "口服", "国产/进口": "国产"}}}, {"index": 37, "title": "半山农 菊粉550g 益生元益生菌高水溶性膳食纤维 优质菊粉低聚果糖", "ShopName": "半山农京东自营旗舰店", "DetailsUrl": "https://item.jd.com/100053309578.html", "price": "99.00", "imgUrl": null, "统计信息": {"好评数": "3.9万+", "好评率": "98%", "差评": "200+", "追评数": "200+", "总评论数": "10万+", "评分统计": {"1星数": 200, "2星数": 85, "3星数": 200, "4星数": 500, "5星数": 20000}, "商品信息": {"品牌信息": "半山农", "商品名称": "半山农菊粉", "商品编号": "100053309578", "包装形式": "罐装", "类别": "其他", "国产/进口": "国产"}}}, {"index": 38, "title": "奥利司他胶囊排油减肥品正国药准字男女通用肥胖症药减肥药强效减肥药快瘦腿减脂肪瘦肚子燃脂减重瘦身雅塑 1盒", "ShopName": "全奇远大药房旗舰店", "DetailsUrl": "https://item.jd.com/10099655754038.html", "price": "7.20", "imgUrl": null, "统计信息": {"好评数": "0", "好评率": "100%", "差评": "0", "追评数": "0", "总评论数": "1", "评分统计": {"1星数": 0, "2星数": 0, "3星数": 0, "4星数": 0, "5星数": 0}, "商品信息": {"品牌信息": "雅塑", "商品名称": "奥利司他胶囊排油减肥品正国药准字男女通用肥胖症药减肥药强效减肥药快瘦腿减脂肪瘦肚子燃脂减重瘦身雅塑 1盒", "商品编号": "10099655754038", "店铺": " 全奇远大药房旗舰店", "适用人群": "成人", "类别": "西药", "药品剂型": "胶囊剂", "使用方法": "口服", "国产/进口": "国产"}}}, {"index": 39, "title": "减肥瘦肚子燃脂 治肥胖症 减肥瘦身湿气大顽固性肥胖瘦大肚子 中药减肥药强效减大肚子 防风通圣丸 3盒祛湿肥胖", "ShopName": "艺妃娇洛阳大药房旗舰店", "DetailsUrl": "https://item.jd.com/10100033831174.html", "price": "29.80", "imgUrl": null, "统计信息": {"好评数": "10+", "好评率": "100%", "差评": "0", "追评数": "0", "总评论数": "16", "评分统计": {"1星数": 0, "2星数": 0, "3星数": 0, "4星数": 0, "5星数": 11}, "商品信息": {"品牌信息": "立效", "商品名称": "减肥瘦肚子燃脂 治肥胖症 减肥瘦身湿气大顽固性肥胖瘦大肚子 中药减肥药强效减大肚子减肥 防风通圣丸 3盒祛湿药肥胖", "商品编号": "10100033831174", "店铺": " 艺妃娇洛阳大药房旗舰店", "货号": "ksn", "药品剂型": "丸剂", "国产/进口": "国产", "适用人群": "儿童", "类别": "中成药", "使用方法": "口服", "适用症状": "便秘"}}}, {"index": 40, "title": "[同仁堂] 轻身消胖丸 720丸/盒 3盒装", "ShopName": "医瑞佳大药房旗舰店", "DetailsUrl": "https://item.jd.com/10096542740048.html", "price": "560.00", "imgUrl": null, "统计信息": {"好评数": "40+", "好评率": "83%", "差评": "5", "追评数": "6", "总评论数": "200+", "评分统计": {"1星数": 5, "2星数": 0, "3星数": 3, "4星数": 0, "5星数": 40}, "商品信息": {"品牌信息": "未知", "商品名称": "[同仁堂] 轻身消胖丸 720丸/盒 3盒装", "商品编号": "10096542740048", "店铺": " 医瑞佳大药房旗舰店", "货号": "021984", "药品剂型": "丸剂", "类别": "中成药", "类型": "处方药", "适用人群": "成人", "使用方法": "口服", "国产/进口": "国产"}}}, {"index": 41, "title": "治肥胖症强效減肥药快中药减肥药祛湿排毒去除湿气瘦大肚子去除脂肪湿气重顽固性肥胖调理中成药归脾丸 一盒装【男女通用相当猛】", "ShopName": "梦尚丽洛阳大药房旗舰店", "DetailsUrl": "https://item.jd.com/10105488364361.html", "price": "12.90", "imgUrl": null, "统计信息": {"好评数": "0", "好评率": "100%", "差评": "0", "追评数": "0", "总评论数": "0", "评分统计": {"1星数": 0, "2星数": 0, "3星数": 0, "4星数": 0, "5星数": 0}, "商品信息": {"品牌信息": "瑞华", "商品名称": "治肥胖症强效減肥药快中药减肥药祛湿排毒去除湿气瘦大肚子去除脂肪湿气重顽固性肥胖调理中成药归脾丸 一盒装【男女通用减肥相当猛】", "商品编号": "10105488364361", "店铺": " 梦尚丽洛阳大药房旗舰店", "类别": "中成药", "适用人群": "通用", "药品剂型": "丸剂", "使用方法": "口服", "国产/进口": "国产"}}}, {"index": 42, "title": "奥利司他胶囊 60mg*24粒 减肥药 减脂肪 减体重 塑身排油减肥随餐一粒 10盒装", "ShopName": "迈恻亦大药房旗舰店", "DetailsUrl": "https://item.jd.com/10098203788089.html", "price": "485.00", "imgUrl": null, "统计信息": {"好评数": "40+", "好评率": "89%", "差评": "1", "追评数": "0", "总评论数": "200+", "评分统计": {"1星数": 1, "2星数": 0, "3星数": 4, "4星数": 2, "5星数": 42}, "商品信息": {"品牌信息": "舒尔佳", "商品名称": "奥利司他胶囊 60mg*24粒  减肥药 减脂肪 减体重 塑身排油减肥随餐一粒 10盒装", "商品编号": "10098203788089", "店铺": " 迈恻亦大药房旗舰店", "货号": "2", "药品剂型": "胶囊剂", "类别": "处方药", "国产/进口": "国产"}}}, {"index": 43, "title": "佰纳吉享受压片糖果咀嚼酵素片代餐轻零食 30片", "ShopName": "超前食品专营店", "DetailsUrl": "https://item.jd.com/10029282240781.html", "price": "135.00", "imgUrl": null, "统计信息": {"好评数": "7", "好评率": "100%", "差评": "0", "追评数": "1", "总评论数": "32", "评分统计": {"1星数": 0, "2星数": 0, "3星数": 0, "4星数": 0, "5星数": 7}, "商品信息": {"品牌信息": "佰纳吉（BIO ENERGY）", "商品名称": "佰纳吉享受压片糖果咀嚼酵素片代餐轻零食 30片", "商品编号": "10029282240781", "店铺": " 超前食品专营店", "是否保健食品": "营养膳食补充剂（非食健字）", "类别": "咀嚼片", "剂型": "片剂", "包装形式": "盒装", "国产/进口": "进口"}}}, {"index": 44, "title": "治肥胖症减肥药】减肥瘦肚子燃脂中药减肥全身瘦大肚子肥胖脂肪多湿气重健脾胃排油专用维生素B1片 1瓶装", "ShopName": "奢佰购大药房官方旗舰店", "DetailsUrl": "https://item.jd.com/10101379444412.html", "price": "9.76", "imgUrl": null, "统计信息": {"好评数": "20+", "好评率": "100%", "差评": "0", "追评数": "1", "总评论数": "67", "评分统计": {"1星数": 0, "2星数": 0, "3星数": 0, "4星数": 0, "5星数": 29}, "商品信息": {"品牌信息": "未知", "商品名称": "治肥胖症减肥药】减肥瘦肚子燃脂中药减肥全身瘦大肚子肥胖脂肪多湿气重健脾胃排油专用药维生素B1片 1瓶装", "商品编号": "10101379444412", "店铺": " 奢佰购大药房官方旗舰店", "货号": "kjn", "类别": "西药", "药品剂型": "片剂", "适用人群": "通用，成人", "使用方法": "口服", "国产/进口": "国产"}}}, {"index": 45, "title": "减肥药强效减肥药快减肥瘦肚子燃脂减肥产品正不品反弹女性快速减肥瘦身产品正不品反弹快速奥利司他胶囊 1瓶装", "ShopName": "热潮奴大药房旗舰店", "DetailsUrl": "https://item.jd.com/10099581484145.html", "price": "22.00", "imgUrl": null, "统计信息": {"好评数": "10+", "好评率": "100%", "差评": "0", "追评数": "1", "总评论数": "18", "评分统计": {"1星数": 0, "2星数": 0, "3星数": 0, "4星数": 0, "5星数": 15}, "商品信息": {"品牌信息": "雅塑", "商品名称": "减肥药强效减肥药快减肥瘦肚子燃脂减肥产品正不品反弹女性快速减肥瘦身产品正不品反弹快速减肥奥利司他胶囊 1瓶装", "商品编号": "10099581484145", "店铺": " 热潮奴大药房旗舰店", "药品剂型": "胶囊剂", "适用人群": "成人", "类别": "非处方药，西药", "使用方法": "口服", "国产/进口": "国产"}}}, {"index": 46, "title": "治肥胖症中药减肥药强效减肥药快肚子大湿气重湿气大肚子肥胖体重超标减不下去肥祛湿排毒专用 防风通圣丸 防风通圣丸*2+龙胆泻肝片*2【不胖不", "ShopName": "花丛懒大药房旗舰店", "DetailsUrl": "https://item.jd.com/10105579551085.html", "price": "51.50", "imgUrl": null, "统计信息": {"好评数": "0", "好评率": "100%", "差评": "0", "追评数": "0", "总评论数": "0", "评分统计": {"1星数": 0, "2星数": 0, "3星数": 0, "4星数": 0, "5星数": 0}, "商品信息": {"品牌信息": "立效", "商品名称": "治肥胖症中药减肥药强效减肥药快肚子大湿气重湿气大肚子肥胖体重超标减不下去肥祛湿排毒专用药 防风通圣丸 防风通圣丸*2+龙胆泻肝片*2【不胖不要用】", "商品编号": "10105579551085", "店铺": " 花丛懒大药房旗舰店", "货号": "张廷玉", "国产/进口": "国产", "药品剂型": "丸剂"}}}, {"index": 47, "title": "舒尔佳 奥利司他胶囊120mg*7粒 减脂减重 减肥药 塑身排油瘦身 治疗肥胖", "ShopName": "京东大药房", "DetailsUrl": "https://item.jd.com/4321270.html", "price": "49.90", "imgUrl": null, "统计信息": {"好评数": "16万+", "好评率": "97%", "差评": "2300+", "追评数": "2600+", "总评论数": "50万+", "评分统计": {"1星数": 2000, "2星数": 500, "3星数": 1000, "4星数": 1000, "5星数": 100000}, "商品信息": {"品牌信息": "舒尔佳", "商品名称": "舒尔佳奥利司他胶囊", "商品编号": "4321270", "货号": "BOF005031C", "类别": "西药", "药品剂型": "胶囊剂", "适用人群": "通用", "使用方法": "口服", "国产/进口": "国产"}}}, {"index": 48, "title": "ISA 奥利司他胶囊2粒 用于18岁及以上成人肥胖或体重超重患者治疗 60mg*2粒*3盒", "ShopName": "言闻大药房官方旗舰店", "DetailsUrl": "https://item.jd.com/10082366750131.html", "price": "99.00", "imgUrl": null, "统计信息": {"好评数": "10+", "好评率": "86%", "差评": "2", "追评数": "0", "总评论数": "200+", "评分统计": {"1星数": 2, "2星数": 0, "3星数": 1, "4星数": 3, "5星数": 16}, "商品信息": {"品牌信息": "ISA", "商品名称": "ISA 奥利司他胶囊2粒 用于18岁及以上成人肥胖或体重超重患者治疗 60mg*2粒*3盒", "商品编号": "10082366750131", "店铺": " 言闻大药房官方旗舰店", "适用人群": "成人", "药品剂型": "胶囊剂", "类别": "其他", "使用方法": "口服", "国产/进口": "国产"}}}, {"index": 49, "title": "儿歌安润膳食纤维综合果蔬粉3.5g*20", "ShopName": "儿歌京东自营官方旗舰店", "DetailsUrl": "https://item.jd.com/8626545.html", "price": "188.00", "imgUrl": null, "统计信息": {"好评数": "2200+", "好评率": "98%", "差评": "10", "追评数": "10+", "总评论数": "1万+", "评分统计": {"1星数": 10, "2星数": 7, "3星数": 16, "4星数": 24, "5星数": 1000}, "商品信息": {"品牌信息": "儿歌", "商品名称": "儿歌儿歌安润综合果蔬粉益生菌固体饮料", "商品编号": "8626545", "是否保健食品": "营养膳食补充剂（非食健字）", "类别": "固体饮料", "剂型": "粉剂", "包装形式": "盒装", "国产/进口": "国产"}}}, {"index": 50, "title": "减肥药 强效减肥药快减肥瘦肚子燃脂减肥产品正不品反弹女性快速减肥排油减脂瘦肚子瘦腿瘦全身奥利司他胶囊 3盒装【排油燃脂】", "ShopName": "璀冠洛阳大药房旗舰店", "DetailsUrl": "https://item.jd.com/10105408169964.html", "price": "50.76", "imgUrl": null, "统计信息": {"好评数": "0", "好评率": "100%", "差评": "0", "追评数": "0", "总评论数": "0", "评分统计": {"1星数": 0, "2星数": 0, "3星数": 0, "4星数": 0, "5星数": 0}, "商品信息": {"品牌信息": "雅塑", "商品名称": "减肥药 强效减肥药快减肥瘦肚子燃脂减肥产品正不品反弹女性快速减肥排油减脂瘦肚子瘦腿瘦全身奥利司他胶囊 3盒装【排油燃脂】", "商品编号": "10105408169964", "店铺": " 璀冠洛阳大药房旗舰店", "类别": "西药", "适用人群": "成人", "药品剂型": "胶囊剂", "使用方法": "口服", "国产/进口": "国产"}}}, {"index": 51, "title": "减肥药强效减肥药快瘦肚子燃脂瘦身排油减脂暴瘦肥胖大肚子瘦腰瘦腿治疗肥胖奥利司他胶囊 三盒装-瘦肚瘦腿", "ShopName": "洁嫣南洛阳大药房旗舰店", "DetailsUrl": "https://item.jd.com/10098353240321.html", "price": "51.50", "imgUrl": null, "统计信息": {"好评数": "20+", "好评率": "100%", "差评": "0", "追评数": "1", "总评论数": "54", "评分统计": {"1星数": 0, "2星数": 0, "3星数": 0, "4星数": 1, "5星数": 28}, "商品信息": {"品牌信息": "雅塑", "商品名称": "减肥药强效减肥药快瘦肚子燃脂瘦身排油减脂暴瘦肥胖大肚子瘦腰瘦腿治疗肥胖奥利司他胶囊 三盒装-瘦肚瘦腿", "商品编号": "10098353240321", "店铺": " 洁嫣南洛阳大药房旗舰店", "货号": "m", "类别": "西药", "药品剂型": "胶囊剂", "适用人群": "成人", "使用方法": "口服", "国产/进口": "国产"}}}, {"index": 52, "title": "舒尔佳奥利司他胶囊 0.12g*7粒盒 减肥药减重减脂治疗肥胖塑身排油瘦身国药准字 120mg*7粒*10盒（70粒23天量减重优选）", "ShopName": "智祥大药房旗舰店", "DetailsUrl": "https://item.jd.com/10096854383904.html", "price": "179.50", "imgUrl": null, "统计信息": {"好评数": "200+", "好评率": "88%", "差评": "10+", "追评数": "1", "总评论数": "2000+", "评分统计": {"1星数": 14, "2星数": 3, "3星数": 10, "4星数": 10, "5星数": 200}, "商品信息": {"品牌信息": "舒尔佳", "商品名称": "舒尔佳奥利司他胶囊 0.12g*7粒盒 减肥药减重减脂治疗肥胖塑身排油瘦身国药准字 120mg*7粒*10盒（70粒23天量减重优选）", "商品编号": "10096854383904", "店铺": " 智祥大药房旗舰店", "类别": "非处方药，西药", "适用人群": "儿童，老年人，通用，成人", "药品剂型": "胶囊剂", "使用方法": "口服", "国产/进口": "国产"}}}, {"index": 53, "title": "减肥药 强效减肥药快不节食燃脂减脂治顽固肥胖减肥瘦身不运动提高代谢专抗水桶腰大肚子大象腿维生素b2片 1盒装【体验装】", "ShopName": "碧洁莱大药房旗舰店", "DetailsUrl": "https://item.jd.com/10105583978621.html", "price": "21.00", "imgUrl": null, "统计信息": {"好评数": "0", "好评率": "100%", "差评": "0", "追评数": "0", "总评论数": "0", "评分统计": {"1星数": 0, "2星数": 0, "3星数": 0, "4星数": 0, "5星数": 0}, "商品信息": {"品牌信息": "未知", "商品名称": "减肥药 强效减肥药快不节食燃脂减脂治顽固肥胖减肥瘦身不运动提高代谢专抗水桶腰大肚子大象腿维生素b2片 1盒装【体验装】", "商品编号": "10105583978621", "店铺": " 碧洁莱大药房旗舰店", "类别": "西药", "适用人群": "成人", "药品剂型": "片剂", "使用方法": "口服", "国产/进口": "国产"}}}, {"index": 54, "title": "碧生源 奥利司他胶囊0.12g*30粒*2盒用于肥胖或体重超重者的治疗", "ShopName": "京东大药房", "DetailsUrl": "https://item.jd.com/100005733019.html", "price": "288.00", "imgUrl": null, "统计信息": {"好评数": "13万+", "好评率": "97%", "差评": "1900+", "追评数": "2000+", "总评论数": "50万+", "评分统计": {"1星数": 1000, "2星数": 200, "3星数": 1000, "4星数": 1000, "5星数": 100000}, "商品信息": {"品牌信息": "碧生源", "商品名称": "碧生源奥利司他胶囊", "商品编号": "100005733019", "类别": "西药", "药品剂型": "胶囊剂", "适用人群": "通用", "使用方法": "口服", "国产/进口": "国产"}}}, {"index": 55, "title": "Moslate脂肪分解酶 减肥瘦肚子燃脂减脂塑身减肥强效 快速减肥女士瘦腿瘦肚子提高代谢减脂 大基数【5瓶周期装】", "ShopName": "Moslate营养健康海外官方旗舰店", "DetailsUrl": "https://item.jd.com/10095604656998.html", "price": "2040.00", "imgUrl": null, "统计信息": {"好评数": "60+", "好评率": "100%", "差评": "0", "追评数": "2", "总评论数": "100+", "评分统计": {"1星数": 0, "2星数": 0, "3星数": 0, "4星数": 0, "5星数": 60}, "商品信息": {"品牌信息": "MOSLATE", "商品名称": "Moslate脂肪分解酶 减肥瘦肚子燃脂减脂塑身减肥强效 快速减肥女士瘦腿瘦肚子提高代谢减脂 大基数【5瓶周期装】", "商品编号": "10095604656998", "店铺": " Moslate营养健康海外官方旗舰店", "是否保健食品": "营养膳食补充剂（非食健字）", "类别": "咀嚼片", "剂型": "片剂", "包装形式": "盒装", "国产/进口": "进口"}}}, {"index": 56, "title": "仁和奥利司他胶囊减肥药减脂减重排油丸瘦身男女通用暴瘦神器排油抗肥胖大肚子瘦腰瘦腿OTC国药准字 10盒装(90粒一月量)", "ShopName": "圣强大药房旗舰店", "DetailsUrl": "https://item.jd.com/10032329257548.html", "price": "299.00", "imgUrl": null, "统计信息": {"好评数": "2000+", "好评率": "97%", "差评": "30+", "追评数": "50+", "总评论数": "5000+", "评分统计": {"1星数": 38, "2星数": 8, "3星数": 14, "4星数": 21, "5星数": 2000}, "商品信息": {"品牌信息": "仁和", "商品名称": "仁和奥利司他胶囊减肥药减脂减重排油丸瘦身男女通用暴瘦神器排油抗肥胖大肚子瘦腰瘦腿OTC国药准字药 10盒装(90粒一月量)", "商品编号": "10032329257548", "店铺": " 圣强大药房旗舰店", "适用人群": "成人", "类别": "其他", "药品剂型": "胶囊剂", "使用方法": "口服", "国产/进口": "国产"}}}, {"index": 57, "title": "京东国际\n减肥药加速燃脂减肚子排油药强特瘦身女士神器效果快速的不节食运动反弹男生专用意大利原装进口专用 1盒【首次使用激活装】", "ShopName": "PROMOPHARMA医药海外旗舰店", "DetailsUrl": "https://item.jd.com/10098679514044.html", "price": "258.00", "imgUrl": null, "统计信息": {"好评数": "10+", "好评率": "100%", "差评": "0", "追评数": "0", "总评论数": "33", "评分统计": {"1星数": 0, "2星数": 0, "3星数": 0, "4星数": 0, "5星数": 19}, "商品信息": {"品牌信息": "PROMOPHARMA", "商品名称": "减肥药加速燃脂减肚子排油药强特瘦身女士神器效果快速的不节食运动反弹男生专用意大利原装进口专用药 1盒【首次使用激活装】", "商品编号": "10098679514044", "店铺": " PROMOPHARMA医药海外旗舰店", "使用方法": "口服", "药品类型": "西药"}}}, {"index": 58, "title": "治肥胖症强效減肥药快中药减肥药祛湿排毒去除湿气瘦大肚子去除脂肪湿气重顽固性肥胖调理中成药香砂六君丸 1盒【推荐多盒效果更佳】", "ShopName": "暮云深大药房旗舰店", "DetailsUrl": "https://item.jd.com/10096746547694.html", "price": "18.00", "imgUrl": null, "统计信息": {"好评数": "50+", "好评率": "91%", "差评": "4", "追评数": "5", "总评论数": "200+", "评分统计": {"1星数": 4, "2星数": 0, "3星数": 1, "4星数": 1, "5星数": 54}, "商品信息": {"品牌信息": "张恒春", "商品名称": "治肥胖症强效減肥药快中药减肥药祛湿排毒去除湿气瘦大肚子去除脂肪湿气重顽固性肥胖调理中成药香砂六君丸 1盒【推荐多盒效果更佳】", "商品编号": "10096746547694", "店铺": " 暮云深大药房旗舰店", "药品剂型": "丸剂", "适用人群": "成人", "类别": "中成药", "使用方法": "口服", "国产/进口": "国产"}}}, {"index": 59, "title": "减肥药强效减肥药快不节食不运动 瘦肚子不i反弹燃烧脂肪减肥产品女性快速减肥奥利司他胶囊 3盒装【水桶腰大肚子没了】", "ShopName": "璀冠洛阳大药房旗舰店", "DetailsUrl": "https://item.jd.com/10103964554857.html", "price": "56.43", "imgUrl": null, "统计信息": {"好评数": "10+", "好评率": "100%", "差评": "0", "追评数": "0", "总评论数": "13", "评分统计": {"1星数": 0, "2星数": 0, "3星数": 0, "4星数": 0, "5星数": 13}, "商品信息": {"品牌信息": "未知", "商品名称": "减肥药强效减肥药快不节食不运动 瘦肚子不i反弹燃烧脂肪减肥产品女性快速减肥奥利司他胶囊 3盒装【水桶腰大肚子没了】", "商品编号": "10103964554857", "店铺": " 璀冠洛阳大药房旗舰店", "类别": "非处方药，处方药", "适用人群": "成人", "药品剂型": "胶囊剂", "使用方法": "口服", "国产/进口": "国产"}}}, {"index": 60, "title": "艾丽奥利司他胶囊60mg*6粒 用于肥胖或体重超重患者", "ShopName": "京东大药房", "DetailsUrl": "https://item.jd.com/100023699460.html", "price": "9.80", "imgUrl": null, "统计信息": {"好评数": "11万+", "好评率": "97%", "差评": "1400+", "追评数": "800+", "总评论数": "20万+", "评分统计": {"1星数": 1000, "2星数": 200, "3星数": 500, "4星数": 1000, "5星数": 50000}, "商品信息": {"品牌信息": "艾丽", "商品名称": "艾丽奥利司他胶囊", "商品编号": "100023699460", "类别": "西药", "药品剂型": "胶囊剂", "适用人群": "通用", "使用方法": "口服", "国产/进口": "国产"}}}], "len": 60}