{"data": [{"index": 1, "title": "Natrol纳妥白芸豆淀粉酶阻断剂膳食纤维60粒", "ShopName": "Natrol芮特海外京东自营旗舰店", "DetailsUrl": "https://item.jd.com/100012023924.html", "price": "160.00", "imgUrl": "https://img14.360buyimg.com/n7/jfs/t1/63546/37/17450/22561/6281ff7aEca0b20ae/58d47d09e0590e69.jpg.avif", "统计信息": {"好评数": "700+", "好评率": "97%", "差评": "10", "追评数": "10+", "总评论数": "5000+", "评分统计": {"1星数": 10, "2星数": 0, "3星数": 14, "4星数": 13, "5星数": 500}, "商品信息": {"品牌信息": "Natrol", "商品名称": "Natrol60粒/瓶", "商品编号": "100012023924", "是否保健食品": "营养膳食补充剂（非食健字）", "类别": "咀嚼片", "剂型": "片剂", "包装形式": "瓶装", "国产/进口": "进口"}}}, {"index": 2, "title": "治肥胖症中药减肥药强效减肥药快肚子大湿气重湿气大肚子肥胖体重超标减不下去肥祛湿排毒 参苓白术散 3盒*肚子变小了 减重超快", "ShopName": "柏丝卓洛阳大药房旗舰店", "DetailsUrl": "https://item.jd.com/10101989954483.html", "price": "62.50", "imgUrl": "https://img13.360buyimg.com/n7/jfs/t1/199379/4/42571/291409/662a11e0F37969188/a38da5d876fd6616.png.avif", "统计信息": {"好评数": "20+", "好评率": "100%", "差评": "0", "追评数": "0", "总评论数": "35", "评分统计": {"1星数": 0, "2星数": 0, "3星数": 0, "4星数": 0, "5星数": 21}, "商品信息": {"品牌信息": "立效", "商品名称": "治肥胖症中药减肥药强效减肥药快肚子大湿气重湿气大肚子肥胖体重超标减不下去肥祛湿排毒 参苓白术散 3盒*肚子变小了 减重超快", "商品编号": "10101989954483", "店铺": " 柏丝卓洛阳大药房旗舰店", "药品剂型": "散剂", "适用人群": "通用", "类别": "中成药", "使用方法": "口服", "国产/进口": "国产"}}}, {"index": 3, "title": "治肥胖症强效減肥药快中药减肥药祛湿排毒去除湿气瘦大肚子去除脂肪湿气重顽固性肥胖调理中成药 香砂六君丸 1盒【建议多盒服用】", "ShopName": "奢佰购大药房官方旗舰店", "DetailsUrl": "https://item.jd.com/10105559031322.html", "price": "18.00", "imgUrl": "https://img12.360buyimg.com/n7/jfs/t1/211467/23/43121/130234/665d3307F66a59f9d/232dbbcc378d8742.jpg.avif", "统计信息": {"好评数": "0", "好评率": "100%", "差评": "0", "追评数": "0", "总评论数": "0", "评分统计": {"1星数": 0, "2星数": 0, "3星数": 0, "4星数": 0, "5星数": 0}, "商品信息": {"品牌信息": "张恒春", "商品名称": "治肥胖症强效減肥药快中药减肥药祛湿排毒去除湿气瘦大肚子去除脂肪湿气重顽固性肥胖调理中成药 香砂六君丸 1盒【建议多盒服用】", "商品编号": "10105559031322", "店铺": " 奢佰购大药房官方旗舰店", "货号": "kjn", "类别": "中成药", "药品剂型": "丸剂", "适用人群": "成人", "使用方法": "口服", "国产/进口": "国产"}}}, {"index": 4, "title": "京东国际\n生铜减肥药瘦身减肚子排油阻断糖碳脂快速进入燃烧脂肪模式代餐特的能量食品补充剂意大利原装效果进口专用 【生酮】快速酮体加速脂肪氧化", "ShopName": "PROMOPHARMA医药海外旗舰店", "DetailsUrl": "https://item.jd.com/10098002241914.html", "price": "383.00", "imgUrl": "https://img14.360buyimg.com/n7/jfs/t1/183479/29/43189/91119/661f251eF8ff30c0a/164a3563e4ade9a3.jpg.avif", "统计信息": {"好评数": "30+", "好评率": "100%", "差评": "0", "追评数": "1", "总评论数": "37", "评分统计": {"1星数": 0, "2星数": 0, "3星数": 0, "4星数": 0, "5星数": 32}, "商品信息": {"品牌信息": "PROMOPHARMA", "商品名称": "生铜减肥药瘦身减肚子排油阻断糖碳脂快速进入燃烧脂肪模式代餐特的能量食品补充剂意大利原装效果进口专用 【生酮减肥】快速酮体加速脂肪氧化代谢（香草味） 1盒体验装", "商品编号": "10098002241914", "店铺": " PROMOPHARMA医药海外旗舰店", "使用方法": "口服", "药品类型": "西药"}}}, {"index": 5, "title": "[泰华制药] 降脂减肥片 0.4g*36片/盒 5盒装", "ShopName": "贵和祥大药房旗舰店", "DetailsUrl": "https://item.jd.com/10071842419588.html", "price": "57.50", "imgUrl": "https://img13.360buyimg.com/n7/jfs/t1/179594/5/43146/72747/661646a8Fd0d284a2/236b2807e22d2322.png.avif", "统计信息": {"好评数": "200+", "好评率": "95%", "差评": "7", "追评数": "2", "总评论数": "1000+", "评分统计": {"1星数": 7, "2星数": 5, "3星数": 0, "4星数": 5, "5星数": 200}, "商品信息": {"品牌信息": "泰华制药", "商品名称": "[泰华制药] 降脂减肥片 0.4g*36片/盒 5盒装", "商品编号": "10071842419588", "店铺": " 贵和祥大药房旗舰店", "货号": "29711", "类型": "处方药", "药品剂型": "片剂", "类别": "中成药", "国产/进口": "国产"}}}, {"index": 6, "title": "[泰华制药] 降脂减肥片 0.4g*36片/盒 3盒装", "ShopName": "贵和祥大药房旗舰店", "DetailsUrl": "https://item.jd.com/10071842419589.html", "price": "34.80", "imgUrl": "https://img14.360buyimg.com/n7/jfs/t1/225685/17/15535/72747/661646a8F3948ad6c/6f3e73eeb48fd088.png.avif", "统计信息": {"好评数": "200+", "好评率": "95%", "差评": "7", "追评数": "2", "总评论数": "1000+", "评分统计": {"1星数": 7, "2星数": 5, "3星数": 0, "4星数": 5, "5星数": 200}, "商品信息": {"品牌信息": "泰华制药", "商品名称": "[泰华制药] 降脂减肥片 0.4g*36片/盒 3盒装", "商品编号": "10071842419589", "店铺": " 贵和祥大药房旗舰店", "货号": "29711", "类型": "处方药", "药品剂型": "片剂", "类别": "中成药", "国产/进口": "国产"}}}, {"index": 7, "title": "vitavea五合一胶囊", "ShopName": "Vitavea 海外旗舰店", "DetailsUrl": "https://item.jd.com/10073013459689.html", "price": "235.00", "imgUrl": "https://img14.360buyimg.com/n7/jfs/t1/200533/5/38748/125364/64a692d7F30e05787/5eff9bca0525f561.png.avif", "统计信息": {"好评数": "10+", "好评率": "92%", "差评": "1", "追评数": "0", "总评论数": "200+", "评分统计": {"1星数": 1, "2星数": 0, "3星数": 0, "4星数": 0, "5星数": 12}, "商品信息": {"品牌信息": "Vitavea", "商品名称": "Vitavea 法国原装进口五合一胶囊美体控脂紧致塑形 60粒/盒 15日量", "商品编号": "10073013459689", "店铺": " Vitavea 海外旗舰店", "是否保健食品": "营养膳食补充剂（非食健字）", "类别": "固体饮料", "剂型": "片剂", "包装形式": "瓶装", "国产/进口": "进口"}}}, {"index": 8, "title": "[同仁堂] 轻身消胖丸 720丸/盒 1瓶装", "ShopName": "医瑞佳大药房旗舰店", "DetailsUrl": "https://item.jd.com/10096542740050.html", "price": "67.00", "imgUrl": "https://img10.360buyimg.com/n7/jfs/t1/249047/6/9346/51973/664af8f4F38f7069d/2c839868a193276b.png.avif", "统计信息": {"好评数": "40+", "好评率": "83%", "差评": "5", "追评数": "6", "总评论数": "200+", "评分统计": {"1星数": 5, "2星数": 0, "3星数": 3, "4星数": 0, "5星数": 41}, "商品信息": {"品牌信息": "未知", "商品名称": "[同仁堂] 轻身消胖丸 720丸/盒 1瓶装", "商品编号": "10096542740050", "店铺": " 医瑞佳大药房旗舰店", "货号": "021984", "药品剂型": "丸剂", "类别": "中成药", "类型": "处方药", "适用人群": "成人", "使用方法": "口服", "国产/进口": "国产"}}}, {"index": 9, "title": "京东国际\n【挑战月瘦50斤】减肥药排油燃脂瘦身减脂效果产品更快燃烧去脂用搭奥利司他强傚快速瘦腰瘦肚子 美国进口30粒/盒（加强两盒装）", "ShopName": "本岛国际医药海外旗舰店", "DetailsUrl": "https://item.jd.com/10088543349152.html", "price": "188.00", "imgUrl": "https://img12.360buyimg.com/n7/jfs/t1/220231/29/38394/117946/65fe768cFae552ecd/a86f32051617c0ae.jpg.avif", "统计信息": {"好评数": "80+", "好评率": "100%", "差评": "0", "追评数": "4", "总评论数": "200+", "评分统计": {"1星数": 0, "2星数": 0, "3星数": 0, "4星数": 2, "5星数": 85}, "商品信息": {"品牌信息": "Lamyus", "商品名称": "【挑战月瘦50斤】减肥药排油燃脂瘦身减脂效果产品更快燃烧去脂用搭奥利司他强傚减肥快速瘦腰瘦肚子 美国进口30粒/盒（加强两盒装）", "商品编号": "10088543349152", "店铺": " 本岛国际医药海外旗舰店", "使用方法": "口服", "药品类型": "其他"}}}, {"index": 10, "title": "治肥胖症强效減肥药快中药减肥药祛湿排毒去除湿气瘦大肚子去除脂肪湿气重顽 固性肥胖调理中成药防风通圣丸 5盒装【多数人的选择】", "ShopName": "艺妃娇大药房旗舰店", "DetailsUrl": "https://item.jd.com/10095083233414.html", "price": "48.30", "imgUrl": "https://img14.360buyimg.com/n7/jfs/t1/202866/26/43475/106250/665d6f96Ff2aae9df/8203e862f74cc000.jpg.avif", "统计信息": {"好评数": "90+", "好评率": "82%", "差评": "10+", "追评数": "0", "总评论数": "500+", "评分统计": {"1星数": 11, "2星数": 3, "3星数": 6, "4星数": 5, "5星数": 89}, "商品信息": {"品牌信息": "立效", "商品名称": "治肥胖症强效減肥药快中药减肥药祛湿排毒去除湿气瘦大肚子去除脂肪湿气重顽 固性肥胖调理中成药防风通圣丸 5盒装【多数人的选择】", "商品编号": "10095083233414", "店铺": " 艺妃娇大药房旗舰店", "货号": "TQ", "适用人群": "成人", "国产/进口": "国产", "类别": "中成药", "药品剂型": "丸剂", "使用方法": "口服", "适用症状": "便秘"}}}, {"index": 11, "title": "治顽固肥胖症 中药减肥药强效减肥药快男女肚子大湿气重脂肪厚体重超重严重肥胖排油瘦身 龙胆泻肝片 1盒【建议多盒使用】", "ShopName": "柏丝卓洛阳大药房旗舰店", "DetailsUrl": "https://item.jd.com/10102716779135.html", "price": "15.50", "imgUrl": "https://img10.360buyimg.com/n7/jfs/t1/237982/7/15298/408298/6635bdd2Ff56a1cb8/4a85005f9e577f62.png.avif", "统计信息": {"好评数": "10+", "好评率": "100%", "差评": "0", "追评数": "1", "总评论数": "22", "评分统计": {"1星数": 0, "2星数": 0, "3星数": 0, "4星数": 0, "5星数": 16}, "商品信息": {"品牌信息": "愉泰", "商品名称": "治顽固肥胖症 中药减肥药强效减肥药快男女肚子大湿气重脂肪厚体重超重严重肥胖排油瘦身 龙胆泻肝片 1盒【建议多盒使用】", "商品编号": "10102716779135", "店铺": " 柏丝卓洛阳大药房旗舰店", "适用人群": "儿童", "类别": "中成药", "药品剂型": "片剂", "使用方法": "口服", "国产/进口": "国产"}}}, {"index": 12, "title": "京东国际\n减肥药瘦肚子燃脂减脂排油丸女生控制食欲瘦身塑身神器特强的效果快速便秘胶囊男士意大利原装进口专用 1盒【首次激活体验装】", "ShopName": "PROMOPHARMA医药海外旗舰店", "DetailsUrl": "https://item.jd.com/10098678343333.html", "price": "383.00", "imgUrl": "https://img13.360buyimg.com/n7/jfs/t1/148613/3/42911/91777/660a30dfF250bc334/5df13a0c94701549.jpg.avif", "统计信息": {"好评数": "20+", "好评率": "96%", "差评": "1", "追评数": "1", "总评论数": "49", "评分统计": {"1星数": 1, "2星数": 0, "3星数": 0, "4星数": 0, "5星数": 25}, "商品信息": {"品牌信息": "PROMOPHARMA", "商品名称": "减肥药瘦肚子燃脂减脂排油丸女生控制食欲瘦身塑身神器特强的效果快速便秘胶囊男士意大利原装进口专用药 1盒【首次激活体验装】", "商品编号": "10098678343333", "店铺": " PROMOPHARMA医药海外旗舰店", "使用方法": "口服", "药品类型": "西药"}}}, {"index": 13, "title": "日本SHUUI修意葛花精华丸酵素小腰丸", "ShopName": "SHUUI修意海外旗舰店", "DetailsUrl": "https://item.jd.com/10067909575641.html", "price": "238.00", "imgUrl": "https://img11.360buyimg.com/n7/jfs/t1/197045/7/33886/50776/645c9218F049b8af9/b21716710eb6b4c7.jpg.avif", "统计信息": {"好评数": "80+", "好评率": "93%", "差评": "4", "追评数": "1", "总评论数": "500+", "评分统计": {"1星数": 4, "2星数": 0, "3星数": 2, "4星数": 1, "5星数": 86}, "商品信息": {"品牌信息": "修意（SHUUI）", "商品名称": "日本SHUUI修意葛花精华丸减肚子分解内脏脂肪膳食纤维阻断酵素小腰丸 推荐3袋一周期 天然葛花精华丸*1袋", "商品编号": "10067909575641", "店铺": " SHUUI修意海外旗舰店", "货号": "JPSU0004", "是否保健食品": "营养膳食补充剂（非食健字）", "类别": "固体饮料", "剂型": "片剂", "包装形式": "袋装", "国产/进口": "进口"}}}, {"index": 14, "title": "吃什么容易减肥药强效减肥药快不节食不运动 瘦肚子不i反弹燃烧脂肪减肥产品女性快速正品奥利司他胶囊 1盒装【尝试装】建议多盒好效果", "ShopName": "德康深圳大药房旗舰店", "DetailsUrl": "https://item.jd.com/10104180769492.html", "price": "20.00", "imgUrl": "https://img12.360buyimg.com/n7/jfs/t1/243657/27/9089/98695/6649d40fF404fa1f4/35b864c113065082.png.avif", "统计信息": {"好评数": "0", "好评率": "0%", "差评": "0", "追评数": "0", "总评论数": "1", "评分统计": {"1星数": 0, "2星数": 0, "3星数": 1, "4星数": 0, "5星数": 0}, "商品信息": {"品牌信息": "雅塑", "商品名称": "吃什么容易减肥药强效减肥药快不节食不运动 瘦肚子不i反弹燃烧脂肪减肥产品女性快速减肥正品奥利司他胶囊 1盒装【尝试装】建议多盒好效果", "商品编号": "10104180769492", "店铺": " 德康深圳大药房旗舰店", "货号": "DH93313", "药品剂型": "胶囊剂", "适用人群": "成人", "类别": "西药", "使用方法": "口服", "国产/进口": "国产"}}}, {"index": 15, "title": "治肥胖症强傚减肥药快抑制食欲不节食不运动去除脂肪减脂肪瘦肚子减肥燃脂减手臂男女排油用药 奥利司他胶囊 3盒【快速掉秤 排油减脂】", "ShopName": "嫣宫媱大药房旗舰店", "DetailsUrl": "https://item.jd.com/10105411762109.html", "price": "56.50", "imgUrl": "https://img14.360buyimg.com/n7/jfs/t1/236146/17/17871/146721/665ad076F4c5e8557/dbe625f410609b6a.jpg.avif", "统计信息": {"好评数": "0", "好评率": "100%", "差评": "0", "追评数": "0", "总评论数": "0", "评分统计": {"1星数": 0, "2星数": 0, "3星数": 0, "4星数": 0, "5星数": 0}, "商品信息": {"品牌信息": "雅塑", "商品名称": "治肥胖症强傚减肥药快抑制食欲不节食不运动去除脂肪减脂肪瘦肚子减肥燃脂减手臂男女排油用药 奥利司他胶囊 3盒【快速掉秤 排油减脂】", "商品编号": "10105411762109", "店铺": " 嫣宫媱大药房旗舰店", "货号": "LL", "类别": "西药", "药品剂型": "胶囊剂", "适用人群": "成人", "使用方法": "口服", "国产/进口": "国产"}}}, {"index": 16, "title": "【治肥胖症的药】减肥药强效减肥药快瘦身祛湿调理顽固性肥胖大肚子提升代谢减脂肪脂肪代谢不佳维生素B1片 单盒", "ShopName": "柏丝卓洛阳大药房旗舰店", "DetailsUrl": "https://item.jd.com/10103716955369.html", "price": "9.60", "imgUrl": "https://img14.360buyimg.com/n7/jfs/t1/188732/24/45662/88125/664414b9F66d8ce5d/b673b39a3438ac0f.jpg.avif", "统计信息": {"好评数": "0", "好评率": "100%", "差评": "0", "追评数": "0", "总评论数": "2", "评分统计": {"1星数": 0, "2星数": 0, "3星数": 0, "4星数": 0, "5星数": 0}, "商品信息": {"品牌信息": "玉威", "商品名称": "【治肥胖症的药】减肥药强效减肥药快瘦身祛湿调理顽固性肥胖大肚子提升代谢减脂肪脂肪代谢不佳维生素B1片 单盒", "商品编号": "10103716955369", "店铺": " 柏丝卓洛阳大药房旗舰店", "药品剂型": "片剂", "适用人群": "儿童", "类别": "西药", "使用方法": "口服", "国产/进口": "国产"}}}, {"index": 17, "title": "代谢差湿气重 提高脂肪代谢药减肥减脂瘦身促进新陈代谢肝胆湿热祛湿瘦肚子湿寒手脚冰凉调理复合维生素B片 1盒【100片】", "ShopName": "目草溪大药房旗舰店", "DetailsUrl": "https://item.jd.com/10102952932270.html", "price": "18.50", "imgUrl": "https://img10.360buyimg.com/n7/jfs/t1/178859/25/44887/166085/66306065F119d37e1/4e3775a80d2f27af.jpg.avif", "统计信息": {"好评数": "5", "好评率": "100%", "差评": "0", "追评数": "0", "总评论数": "13", "评分统计": {"1星数": 0, "2星数": 0, "3星数": 0, "4星数": 0, "5星数": 5}, "商品信息": {"品牌信息": "南岛", "商品名称": "代谢差湿气重 提高脂肪代谢药减肥减脂瘦身促进新陈代谢肝胆湿热祛湿瘦肚子湿寒手脚冰凉调理复合维生素B片 1盒【100片】", "商品编号": "10102952932270", "店铺": " 目草溪大药房旗舰店", "药品剂型": "片剂", "适用人群": "通用", "类别": "西药", "使用方法": "口服", "国产/进口": "国产"}}}, {"index": 18, "title": "清热祛湿颗粒 祛湿排毒去除湿气瘦肚子减重排体内湿寒中药治脾虚湿气重肚子肥大四肢不胖大便不成形口干口苦 1盒【湿气重虚胖 肚子大】", "ShopName": "目草溪大药房旗舰店", "DetailsUrl": "https://item.jd.com/10089902844138.html", "price": "36.00", "imgUrl": "https://img13.360buyimg.com/n7/jfs/t1/136743/31/44236/131374/66138d2aFda27de0c/37a8f0feaa5e8b1a.jpg.avif", "统计信息": {"好评数": "50+", "好评率": "90%", "差评": "2", "追评数": "0", "总评论数": "500+", "评分统计": {"1星数": 2, "2星数": 2, "3星数": 2, "4星数": 3, "5星数": 56}, "商品信息": {"品牌信息": "众生", "商品名称": "清热祛湿颗粒 祛湿排毒去除湿气瘦肚子减重排体内湿寒中药治脾虚湿气重肚子肥大四肢不胖大便不成形口干口苦 1盒【湿气重虚胖 肚子大】", "商品编号": "10089902844138", "店铺": " 目草溪大药房旗舰店", "类别": "中成药", "国产/进口": "国产", "适用人群": "通用", "药品剂型": "颗粒剂", "使用方法": "口服", "适用症状": "食欲不振"}}}, {"index": 19, "title": "[999]奥利司他胶囊 减脂减重 随餐控制体重 男女治疗肥胖", "ShopName": "鲸黛大药房旗舰店", "DetailsUrl": "https://item.jd.com/10102805784767.html", "price": "150.90", "imgUrl": "https://img12.360buyimg.com/n7/jfs/t1/249299/34/8451/197264/66407ab2F62e27408/881a65f8cd7b8289.png.avif", "统计信息": {"好评数": "100+", "好评率": "100%", "差评": "0", "追评数": "4", "总评论数": "100+", "评分统计": {"1星数": 0, "2星数": 0, "3星数": 0, "4星数": 0, "5星数": 100}, "商品信息": {"品牌信息": "三九医药 999", "商品名称": "[999-玖减]奥利司他胶囊 减肥瘦肚子燃脂塑身 减脂减重排油减肥药 强效减肥药快 治疗肥胖 10盒【减脂瘦身】", "商品编号": "10102805784767", "店铺": " 鲸黛大药房旗舰店", "适用人群": "成人", "药品剂型": "胶囊剂", "类别": "西药", "使用方法": "口服", "国产/进口": "国产"}}}, {"index": 20, "title": "[益美佳] 奥利司他胶囊 60mg*7粒 减脂减重 减肥药 塑身排油瘦身治疗肥胖 1盒装【2-3天用量】", "ShopName": "鲁南官方旗舰店", "DetailsUrl": "https://item.jd.com/10041366546178.html", "price": "9.90", "imgUrl": "https://img13.360buyimg.com/n7/jfs/t1/158890/18/26600/97968/6657f46eF08dc9f0e/b0e66f0ea0facb79.jpg.avif", "统计信息": {"好评数": "1200+", "好评率": "95%", "差评": "30+", "追评数": "10+", "总评论数": "5000+", "评分统计": {"1星数": 32, "2星数": 8, "3星数": 23, "4星数": 41, "5星数": 1000}, "商品信息": {"品牌信息": "益美佳", "商品名称": "[益美佳] 奥利司他胶囊 60mg*7粒  减脂减重 减肥药 塑身排油瘦身治疗肥胖 1盒装【2-3天用量】", "商品编号": "10041366546178", "店铺": " 鲁南官方旗舰店", "货号": "A000213399003", "类别": "西药", "药品剂型": "胶囊剂", "适用人群": "成人", "使用方法": "口服", "国产/进口": "国产"}}}, {"index": 21, "title": "雅塑 奥利司他胶囊 排油减肥减脂减重 国药准字OTC减肥药 10盒（1）", "ShopName": "佳药一新大药房官方旗舰店", "DetailsUrl": "https://item.jd.com/10065192193534.html", "price": "409.00", "imgUrl": "https://img14.360buyimg.com/n7/jfs/t1/238403/10/10601/113664/65a0ff1cF21df1f83/353d4fc1eeb4d650.jpg.avif", "统计信息": {"好评数": "800+", "好评率": "96%", "差评": "10+", "追评数": "10+", "总评论数": "5000+", "评分统计": {"1星数": 19, "2星数": 3, "3星数": 11, "4星数": 14, "5星数": 500}, "商品信息": {"品牌信息": "雅塑（yasu）", "商品名称": "雅塑 奥利司他胶囊  排油减肥减脂减重 国药准字OTC减肥药 10盒（1）", "商品编号": "10065192193534", "店铺": " 佳药一新大药房官方旗舰店", "适用人群": "成人", "类别": "非处方药，西药", "药品剂型": "胶囊剂", "使用方法": "口服", "国产/进口": "国产"}}}, {"index": 22, "title": "[同仁堂] 轻身消胖丸 720丸/盒 1瓶装", "ShopName": "为济堂大药房旗舰店", "DetailsUrl": "https://item.jd.com/10096239159288.html", "price": "57.00", "imgUrl": "https://img13.360buyimg.com/n7/jfs/t20270125/246735/4/4106/161330/65b38d2eFd9e2c893/94f65163b1580ad7.png.avif", "统计信息": {"好评数": "10+", "好评率": "85%", "差评": "0", "追评数": "1", "总评论数": "100+", "评分统计": {"1星数": 0, "2星数": 0, "3星数": 2, "4星数": 1, "5星数": 11}, "商品信息": {"品牌信息": "未知", "商品名称": "[同仁堂] 轻身消胖丸 720丸/盒 1瓶装", "商品编号": "10096239159288", "店铺": " 为济堂大药房旗舰店", "货号": "021984", "适用人群": "通用", "药品剂型": "丸剂", "类型": "处方药", "类别": "中成药", "使用方法": "口服", "国产/进口": "国产"}}}, {"index": 23, "title": "艾丽奥利司他胶囊 60mg*6粒用于肥胖或体重超重患者减肥药OTC国药准字减肥药 10盒装【共发60】效期24年11月", "ShopName": "植恩大药房官方旗舰店", "DetailsUrl": "https://item.jd.com/10075252345352.html", "price": "60.00", "imgUrl": "https://img12.360buyimg.com/n7/jfs/t1/194984/15/45467/163781/66431ed0Fea519e90/66f167b1fe2bd299.jpg.avif", "统计信息": {"好评数": "100+", "好评率": "95%", "差评": "4", "追评数": "0", "总评论数": "1000+", "评分统计": {"1星数": 4, "2星数": 0, "3星数": 2, "4星数": 7, "5星数": 100}, "商品信息": {"品牌信息": "艾丽", "商品名称": "艾丽奥利司他胶囊 60mg*6粒用于肥胖或体重超重患者减肥药OTC国药准字减肥药 10盒装【共发60】效期24年11月", "商品编号": "10075252345352", "店铺": " 植恩大药房官方旗舰店", "类别": "西药", "药品剂型": "胶囊剂", "适用人群": "成人", "使用方法": "口服", "国产/进口": "国产"}}}, {"index": 24, "title": "舒尔佳 奥利司他胶囊120mg*96粒 礼盒装 减脂减重 减肥药 塑身排油瘦身 治疗肥胖", "ShopName": "鲁南舒尔佳京东自营官方旗舰店", "DetailsUrl": "https://item.jd.com/100007577583.html", "price": "517.00", "imgUrl": "https://img13.360buyimg.com/n7/jfs/t1/155547/26/41172/107967/665af248F875d2cbf/03d5efcd72552ba5.jpg.avif", "统计信息": {"好评数": "25万+", "好评率": "96%", "差评": "5500+", "追评数": "4900+", "总评论数": "100万+", "评分统计": {"1星数": 5000, "2星数": 1000, "3星数": 2000, "4星数": 2000, "5星数": 200000}, "商品信息": {"品牌信息": "舒尔佳", "商品名称": "舒尔佳奥利司他胶囊", "商品编号": "100007577583", "货号": "BOF005030C", "类别": "西药", "药品剂型": "胶囊剂", "适用人群": "通用", "使用方法": "口服", "国产/进口": "国产"}}}, {"index": 25, "title": "英国 Proven益生菌", "ShopName": "3ChemBio海外卖场店", "DetailsUrl": "https://item.jd.com/10075944658970.html", "price": "224.00", "imgUrl": "https://img10.360buyimg.com/n7/jfs/t1/169399/35/40004/117154/64e3221aF04a12d5f/9d621eaf5bd56ccb.jpg.avif", "统计信息": {"好评数": "300+", "好评率": "98%", "差评": "2", "追评数": "10", "总评论数": "5000+", "评分统计": {"1星数": 2, "2星数": 3, "3星数": 0, "4星数": 8, "5星数": 200}, "商品信息": {"品牌信息": "Pro-Ven", "商品名称": "【港企直营店】Proven瘦身益生菌瘦子菌减肥瘦肚子燃脂纤体胶囊成人肠道调理塑身排油英国进口30粒 瘦身减肥益生菌", "商品编号": "10075944658970", "店铺": " 3ChemBio海外卖场店", "是否保健食品": "营养膳食补充剂（非食健字）", "包装形式": "瓶装", "剂型": "胶囊", "国产/进口": "进口"}}}, {"index": 26, "title": "治严重肥胖症 中药减肥瘦肚子燃脂强傚男女瘦身排油去除多余脂肪快 湿气重去湿气排毒大肚子 龙胆泻肝片 3盒装【快速掉秤】", "ShopName": "视星球洛阳大药房旗舰店", "DetailsUrl": "https://item.jd.com/10101305751605.html", "price": "46.20", "imgUrl": "https://img10.360buyimg.com/n7/jfs/t1/245578/32/7134/119161/661df4d0F349625a4/e1d325185a2a272c.jpg.avif", "统计信息": {"好评数": "80+", "好评率": "96%", "差评": "1", "追评数": "9", "总评论数": "200+", "评分统计": {"1星数": 1, "2星数": 1, "3星数": 1, "4星数": 1, "5星数": 84}, "商品信息": {"品牌信息": "愉泰", "商品名称": "治严重肥胖症 中药减肥瘦肚子燃脂强傚男女瘦身排油去除多余脂肪快\t湿气重去湿气排毒大肚子 龙胆泻肝片 3盒装【快速掉秤】", "商品编号": "10101305751605", "店铺": " 视星球洛阳大药房旗舰店", "货号": "ws", "类别": "中成药", "药品剂型": "片剂", "适用人群": "儿童", "使用方法": "口服", "国产/进口": "国产"}}}, {"index": 27, "title": "仁和奥利司他胶囊减肥药减脂减重排油丸瘦身男女通用暴瘦神器排油抗肥胖大肚子瘦腰瘦腿OTC国药准字 10盒装(90粒一月量)", "ShopName": "圣强大药房旗舰店", "DetailsUrl": "https://item.jd.com/10032329257548.html", "price": "299.00", "imgUrl": "https://img13.360buyimg.com/n7/jfs/t1/122372/12/22288/177138/621888f7E918c5754/e165b9ac55f5565b.jpg.avif", "统计信息": {"好评数": "2000+", "好评率": "97%", "差评": "30+", "追评数": "50+", "总评论数": "5000+", "评分统计": {"1星数": 38, "2星数": 8, "3星数": 14, "4星数": 21, "5星数": 2000}, "商品信息": {"品牌信息": "仁和", "商品名称": "仁和奥利司他胶囊减肥药减脂减重排油丸瘦身男女通用暴瘦神器排油抗肥胖大肚子瘦腰瘦腿OTC国药准字药 10盒装(90粒一月量)", "商品编号": "10032329257548", "店铺": " 圣强大药房旗舰店", "适用人群": "成人", "类别": "其他", "药品剂型": "胶囊剂", "使用方法": "口服", "国产/进口": "国产"}}}, {"index": 28, "title": "[999] 奥利司他胶囊 60mg*25粒/盒 适用于成人体重超重肥胖男女通用 1盒【有效期到2024年7月】", "ShopName": "翝義芢大药房旗舰店", "DetailsUrl": "https://item.jd.com/10105315643045.html", "price": "14.80", "imgUrl": "https://img10.360buyimg.com/n7/jfs/t1/220539/2/41049/51304/66597566F77d9e0c4/457d532db9f4bf9a.jpg.avif", "统计信息": {"好评数": "0", "好评率": "100%", "差评": "0", "追评数": "0", "总评论数": "0", "评分统计": {"1星数": 0, "2星数": 0, "3星数": 0, "4星数": 0, "5星数": 0}, "商品信息": {"品牌信息": "999", "商品名称": "[999] 奥利司他胶囊 60mg*25粒/盒 适用于成人体重超重肥胖男女通用 1盒【有效期到2024年7月】", "商品编号": "10105315643045", "店铺": " 翝義芢大药房旗舰店", "药品剂型": "胶囊剂", "类别": "西药", "适用人群": "成人", "使用方法": "口服", "国产/进口": "国产"}}}, {"index": 29, "title": "雅塑 奥利司他胶囊0.12g*18粒 用于肥胖或体重超重患者的治疗", "ShopName": "雅塑京东自营旗舰店", "DetailsUrl": "https://item.jd.com/100012750382.html", "price": "43.00", "imgUrl": "https://img12.360buyimg.com/n7/jfs/t1/224068/9/19560/117367/6659485eF8b068e75/a5c4f9b4b9fcb67f.jpg.avif", "统计信息": {"好评数": "4900+", "好评率": "96%", "差评": "90+", "追评数": "80+", "总评论数": "2万+", "评分统计": {"1星数": 93, "2星数": 25, "3星数": 60, "4星数": 74, "5星数": 2000}, "商品信息": {"品牌信息": "雅塑（yasu）", "商品名称": "雅塑奥利司他胶囊", "商品编号": "100012750382", "类别": "西药", "药品剂型": "胶囊剂", "适用人群": "通用", "使用方法": "口服", "国产/进口": "国产"}}}, {"index": 30, "title": "碧生源 奥利司他胶囊0.12g*30粒*2盒用于肥胖或体重超重者的治疗", "ShopName": "京东大药房", "DetailsUrl": "https://item.jd.com/100005733019.html", "price": "288.00", "imgUrl": "https://img14.360buyimg.com/n7/jfs/t1/120612/8/43548/200875/65fd1aa7F5a398120/e79ccb17849bb3b7.jpg.avif", "统计信息": {"好评数": "13万+", "好评率": "97%", "差评": "1900+", "追评数": "2000+", "总评论数": "50万+", "评分统计": {"1星数": 1000, "2星数": 200, "3星数": 1000, "4星数": 1000, "5星数": 100000}, "商品信息": {"品牌信息": "碧生源", "商品名称": "碧生源奥利司他胶囊", "商品编号": "100005733019", "类别": "西药", "药品剂型": "胶囊剂", "适用人群": "通用", "使用方法": "口服", "国产/进口": "国产"}}}, {"index": 31, "title": "vitavea五合一胶囊", "ShopName": "Vitavea 海外旗舰店", "DetailsUrl": "https://item.jd.com/10073013459689.html", "price": "235.00", "imgUrl": "https://img14.360buyimg.com/n7/jfs/t1/200533/5/38748/125364/64a692d7F30e05787/5eff9bca0525f561.png.avif", "统计信息": {"好评数": "10+", "好评率": "92%", "差评": "1", "追评数": "0", "总评论数": "200+", "评分统计": {"1星数": 1, "2星数": 0, "3星数": 0, "4星数": 0, "5星数": 12}, "商品信息": {"品牌信息": "Vitavea", "商品名称": "Vitavea 法国原装进口五合一胶囊美体控脂紧致塑形 60粒/盒 15日量", "商品编号": "10073013459689", "店铺": " Vitavea 海外旗舰店", "是否保健食品": "营养膳食补充剂（非食健字）", "类别": "固体饮料", "剂型": "片剂", "包装形式": "瓶装", "国产/进口": "进口"}}}, {"index": 32, "title": "治肥胖症强效减肥药快中药减肥药祛湿排毒去除湿气瘦大肚子去除脂肪湿气重顽固性肥胖调理中成药防风通圣丸 1盒装【中药】", "ShopName": "墨如烟大药房旗舰店", "DetailsUrl": "https://item.jd.com/10102959291197.html", "price": "10.75", "imgUrl": "https://img12.360buyimg.com/n7/jfs/t1/177943/31/47027/95559/665d738fFa962b43c/10134e092b96f5c9.jpg.avif", "统计信息": {"好评数": "2", "好评率": "100%", "差评": "0", "追评数": "0", "总评论数": "2", "评分统计": {"1星数": 0, "2星数": 0, "3星数": 0, "4星数": 0, "5星数": 2}, "商品信息": {"品牌信息": "立效", "商品名称": "治肥胖症强效减肥药快中药减肥药祛湿排毒去除湿气瘦大肚子去除脂肪湿气重顽固性肥胖调理中成药防风通圣丸 1盒装【中药减肥】", "商品编号": "10102959291197", "店铺": " 墨如烟大药房旗舰店", "货号": "kjn", "类别": "中成药", "适用症状": "便秘", "药品剂型": "丸剂", "适用人群": "成人", "使用方法": "口服", "国产/进口": "国产"}}}, {"index": 33, "title": "治肥胖症减肥药】减肥瘦肚子燃脂中药减肥强傚快不节食不运动祛湿排毒去除湿气瘦肚子中成药 龙胆泻肝片 3盒装【轻松享瘦】", "ShopName": "视星球洛阳大药房旗舰店", "DetailsUrl": "https://item.jd.com/10101792534646.html", "price": "47.40", "imgUrl": "https://img11.360buyimg.com/n7/jfs/t1/156860/9/44031/75087/66272e31Fe9df9fb4/9b2d5b235e30bdb3.jpg.avif", "统计信息": {"好评数": "10+", "好评率": "100%", "差评": "0", "追评数": "4", "总评论数": "28", "评分统计": {"1星数": 0, "2星数": 0, "3星数": 0, "4星数": 0, "5星数": 19}, "商品信息": {"品牌信息": "愉泰", "商品名称": "治肥胖症减肥药】减肥瘦肚子燃脂中药减肥强傚快不节食不运动祛湿排毒去除湿气瘦肚子中成药 龙胆泻肝片 3盒装【轻松享瘦】", "商品编号": "10101792534646", "店铺": " 视星球洛阳大药房旗舰店", "货号": "ws", "适用人群": "儿童", "类别": "中成药", "药品剂型": "片剂", "使用方法": "口服", "国产/进口": "国产"}}}, {"index": 34, "title": "仁和 奥利司他胶囊 60mg*21粒 用于18岁及以上成人体重超重的治疗（好效期到2026年5月） 1盒装", "ShopName": "叮当极致大药房旗舰店-释放", "DetailsUrl": "https://item.jd.com/10101237788351.html", "price": "45.00", "imgUrl": "https://img11.360buyimg.com/n7/jfs/t1/94643/18/47848/77514/65e91d5eF5851b21d/b15ad8af4917f5ef.jpg.avif", "统计信息": {"好评数": "4", "好评率": "100%", "差评": "0", "追评数": "0", "总评论数": "100+", "评分统计": {"1星数": 0, "2星数": 0, "3星数": 0, "4星数": 0, "5星数": 4}, "商品信息": {"品牌信息": "仁和", "商品名称": "仁和 奥利司他胶囊 60mg*21粒 用于18岁及以上成人体重超重的治疗（好效期到2026年5月） 1盒装", "商品编号": "10101237788351", "店铺": " 叮当极致大药房旗舰店-释放", "货号": "02100679", "适用人群": "成人", "类别": "其他", "药品剂型": "胶囊剂", "使用方法": "口服", "国产/进口": "国产"}}}, {"index": 35, "title": "[雅塑] 奥利司他胶囊 0.12g减肥药减脂减重治疗体重超重肥胖患者国药准字植恩生物OTC 7盒装/共发81", "ShopName": "植恩大药房官方旗舰店", "DetailsUrl": "https://item.jd.com/10025449485356.html", "price": "196.00", "imgUrl": "https://img11.360buyimg.com/n7/jfs/t1/216987/34/32392/172575/66594131F49d47195/4e003332940edaa6.jpg.avif", "统计信息": {"好评数": "1800+", "好评率": "96%", "差评": "30+", "追评数": "40+", "总评论数": "1万+", "评分统计": {"1星数": 34, "2星数": 11, "3星数": 14, "4星数": 12, "5星数": 1000}, "商品信息": {"品牌信息": "雅塑（yasu）", "商品名称": "[雅塑] 奥利司他胶囊 0.12g减肥药减脂减重治疗体重超重肥胖患者国药准字植恩生物OTC 7盒装/共发81", "商品编号": "10025449485356", "店铺": " 植恩大药房官方旗舰店", "药品剂型": "胶囊剂", "类别": "非处方药", "适用人群": "通用", "使用方法": "口服", "国产/进口": "国产"}}}, {"index": 36, "title": "新陈代谢慢导致肥胖症 减肥特好药瘦身瘦大肚子去除脂肪脂肪代谢不佳就用 复合维生素B片 1瓶基础【趁早用】", "ShopName": "暮云深大药房旗舰店", "DetailsUrl": "https://item.jd.com/10093746144955.html", "price": "15.80", "imgUrl": null, "统计信息": {"好评数": "6", "好评率": "100%", "差评": "0", "追评数": "0", "总评论数": "47", "评分统计": {"1星数": 0, "2星数": 0, "3星数": 0, "4星数": 0, "5星数": 6}, "商品信息": {"品牌信息": "南岛", "商品名称": "新陈代谢慢导致肥胖症 减肥特好药瘦身瘦大肚子去除脂肪脂肪代谢不佳就用 复合维生素B片 1瓶基础【趁早用】", "商品编号": "10093746144955", "店铺": " 暮云深大药房旗舰店", "国产/进口": "国产", "药品剂型": "片剂"}}}, {"index": 37, "title": "英国 Proven益生菌", "ShopName": "3ChemBio海外卖场店", "DetailsUrl": "https://item.jd.com/10075944658970.html", "price": "224.00", "imgUrl": null, "统计信息": {"好评数": "300+", "好评率": "98%", "差评": "2", "追评数": "10", "总评论数": "5000+", "评分统计": {"1星数": 2, "2星数": 3, "3星数": 0, "4星数": 8, "5星数": 200}, "商品信息": {"品牌信息": "Pro-Ven", "商品名称": "【港企直营店】Proven瘦身益生菌瘦子菌减肥瘦肚子燃脂纤体胶囊成人肠道调理塑身排油英国进口30粒 瘦身减肥益生菌", "商品编号": "10075944658970", "店铺": " 3ChemBio海外卖场店", "是否保健食品": "营养膳食补充剂（非食健字）", "包装形式": "瓶装", "剂型": "胶囊", "国产/进口": "进口"}}}, {"index": 38, "title": "舒尔佳奥利司他胶囊 0.12g*7粒盒 减肥药减重减脂治疗肥胖塑身排油瘦身国药准字 120mg*7粒*10盒（70粒23天量减重优选）", "ShopName": "智祥大药房旗舰店", "DetailsUrl": "https://item.jd.com/10096854383904.html", "price": "179.50", "imgUrl": null, "统计信息": {"好评数": "200+", "好评率": "88%", "差评": "10+", "追评数": "1", "总评论数": "2000+", "评分统计": {"1星数": 14, "2星数": 3, "3星数": 10, "4星数": 10, "5星数": 200}, "商品信息": {"品牌信息": "舒尔佳", "商品名称": "舒尔佳奥利司他胶囊 0.12g*7粒盒 减肥药减重减脂治疗肥胖塑身排油瘦身国药准字 120mg*7粒*10盒（70粒23天量减重优选）", "商品编号": "10096854383904", "店铺": " 智祥大药房旗舰店", "类别": "非处方药，西药", "适用人群": "儿童，老年人，通用，成人", "药品剂型": "胶囊剂", "使用方法": "口服", "国产/进口": "国产"}}}, {"index": 39, "title": "舒尔佳奥利司他胶囊0.12g*21粒/盒 OTC减肥药减脂减重治疗肥胖塑身排油瘦身国药准字LN 7粒 x 1盒【共7粒】", "ShopName": "广盛远大药房旗舰店", "DetailsUrl": "https://item.jd.com/10103152125917.html", "price": "19.90", "imgUrl": null, "统计信息": {"好评数": "6", "好评率": "100%", "差评": "0", "追评数": "0", "总评论数": "11", "评分统计": {"1星数": 0, "2星数": 0, "3星数": 0, "4星数": 0, "5星数": 6}, "商品信息": {"品牌信息": "舒尔佳", "商品名称": "舒尔佳奥利司他胶囊0.12g*21粒/盒 OTC减肥药减脂减重治疗肥胖塑身排油瘦身国药准字LN 7粒 x 1盒【共7粒】", "商品编号": "10103152125917", "店铺": " 广盛远大药房旗舰店", "货号": "1230201020", "适用人群": "成人", "类别": "西药", "药品剂型": "胶囊剂", "使用方法": "口服", "国产/进口": "国产"}}}, {"index": 40, "title": "艾丽奥利司他胶囊 60mg*6粒用于肥胖或体重超重患者减肥药OTC国药准字减肥药 1盒装【共发6】", "ShopName": "植恩大药房官方旗舰店", "DetailsUrl": "https://item.jd.com/10075252345349.html", "price": "7.90", "imgUrl": null, "统计信息": {"好评数": "100+", "好评率": "95%", "差评": "4", "追评数": "0", "总评论数": "1000+", "评分统计": {"1星数": 4, "2星数": 0, "3星数": 2, "4星数": 7, "5星数": 100}, "商品信息": {"品牌信息": "艾丽", "商品名称": "艾丽奥利司他胶囊 60mg*6粒用于肥胖或体重超重患者减肥药OTC国药准字减肥药 1盒装【共发6】", "商品编号": "10075252345349", "店铺": " 植恩大药房官方旗舰店", "类别": "西药", "药品剂型": "胶囊剂", "适用人群": "成人", "使用方法": "口服", "国产/进口": "国产"}}}, {"index": 41, "title": "脂肪代谢慢肥胖肚子大减肥药 强效减肥药快瘦身减肚子提高新陈代谢燃烧脂肪治肥胖症 维生素b1片 3盒装/提高新陈代谢", "ShopName": "赞译洛阳大药房旗舰店", "DetailsUrl": "https://item.jd.com/10103751821310.html", "price": "26.30", "imgUrl": null, "统计信息": {"好评数": "3", "好评率": "100%", "差评": "0", "追评数": "0", "总评论数": "3", "评分统计": {"1星数": 0, "2星数": 0, "3星数": 0, "4星数": 0, "5星数": 3}, "商品信息": {"品牌信息": "蜀中", "商品名称": "脂肪代谢慢肥胖肚子大减肥药 强效减肥药快瘦身减肚子提高新陈代谢燃烧脂肪治肥胖症 维生素b1片 3盒装/提高新陈代谢", "商品编号": "10103751821310", "店铺": " 赞译洛阳大药房旗舰店", "适用人群": "儿童", "药品剂型": "片剂", "类别": "西药", "使用方法": "口服", "国产/进口": "国产"}}}, {"index": 42, "title": "[雅塑] 奥利司他胶囊 60mg*4粒 用于肥胖或体重超重患者 减肥药 5盒装", "ShopName": "露妍堂大药房旗舰店", "DetailsUrl": "https://item.jd.com/10090515962021.html", "price": "35.00", "imgUrl": null, "统计信息": {"好评数": "2", "好评率": "100%", "差评": "0", "追评数": "0", "总评论数": "10", "评分统计": {"1星数": 0, "2星数": 0, "3星数": 0, "4星数": 0, "5星数": 2}, "商品信息": {"品牌信息": "雅塑", "商品名称": "[雅塑] 奥利司他胶囊 60mg*4粒 用于肥胖或体重超重患者 减肥药 5盒装", "商品编号": "10090515962021", "店铺": " 露妍堂大药房旗舰店", "药品剂型": "胶囊剂", "适用人群": "成人", "类别": "西药", "使用方法": "口服", "国产/进口": "国产"}}}, {"index": 43, "title": "【新西兰进口】Naturies白芸豆纤体饮", "ShopName": "Naturies营养保健海外旗舰店", "DetailsUrl": "https://item.jd.com/10099222588547.html", "price": "780.00", "imgUrl": null, "统计信息": {"好评数": "90+", "好评率": "100%", "差评": "0", "追评数": "8", "总评论数": "100+", "评分统计": {"1星数": 0, "2星数": 0, "3星数": 0, "4星数": 0, "5星数": 94}, "商品信息": {"品牌信息": "Naturies", "商品名称": "【新西兰进口】Naturies白芸豆左旋肉碱阻断剂断糖抗糖减肥瘦身瘦肚子燃脂脂肪大餐碳水膳食纤维代餐 1盒", "商品编号": "10099222588547", "店铺": " Naturies营养保健海外旗舰店", "是否保健食品": "营养膳食补充剂（非食健字）", "类别": "液体饮料", "剂型": "液体", "包装形式": "盒装", "国产/进口": "进口"}}}, {"index": 44, "title": "奥利司他胶囊排油减肥减肥药强傚效减肥药快男女瘦腿减脂肪减肥瘦肚子减重瘦身 10盒【二周用量】效果很不错", "ShopName": "黛参苓大药房官方旗舰店", "DetailsUrl": "https://item.jd.com/10081918594065.html", "price": "93.50", "imgUrl": null, "统计信息": {"好评数": "400+", "好评率": "86%", "差评": "40+", "追评数": "6", "总评论数": "2000+", "评分统计": {"1星数": 41, "2星数": 11, "3星数": 15, "4星数": 22, "5星数": 200}, "商品信息": {"品牌信息": "雅塑", "商品名称": "奥利司他胶囊排油减肥减肥药强傚效减肥药快男女瘦腿减脂肪减肥瘦肚子减重瘦身 10盒【二周用量】效果很不错", "商品编号": "10081918594065", "店铺": " 黛参苓大药房官方旗舰店", "货号": "82536", "适用人群": "成人", "类别": "非处方药，其他", "药品剂型": "胶囊剂", "使用方法": "口服", "国产/进口": "国产"}}}, {"index": 45, "title": "治肥胖症强效减肥药快中药减肥药祛湿排毒去除湿气瘦大肚子去除脂肪湿气重顽固性肥胖调理中成药防风通圣丸 1盒【建议多盒服用】", "ShopName": "蓓方益大药房旗舰店", "DetailsUrl": "https://item.jd.com/10104678980899.html", "price": "13.50", "imgUrl": null, "统计信息": {"好评数": "3", "好评率": "100%", "差评": "0", "追评数": "0", "总评论数": "3", "评分统计": {"1星数": 0, "2星数": 0, "3星数": 0, "4星数": 0, "5星数": 3}, "商品信息": {"品牌信息": "立效", "商品名称": "治肥胖症强效减肥药快中药减肥药祛湿排毒去除湿气瘦大肚子去除脂肪湿气重顽固性肥胖调理中成药防风通圣丸 1盒【建议多盒服用】", "商品编号": "10104678980899", "店铺": " 蓓方益大药房旗舰店", "适用人群": "成人", "适用症状": "便秘", "药品剂型": "丸剂", "类别": "中成药", "使用方法": "口服", "国产/进口": "国产"}}}, {"index": 46, "title": "肚子大湿气重】用于脾胃虚弱湿气重引起虚胖肚大脂肪堆积 参苓白术散可搭保济药丸奥利i司他 3盒装【脾胃虚弱肚子大】", "ShopName": "洛骆堂旗舰店", "DetailsUrl": "https://item.jd.com/10082069438797.html", "price": "65.00", "imgUrl": null, "统计信息": {"好评数": "10", "好评率": "100%", "差评": "0", "追评数": "0", "总评论数": "40", "评分统计": {"1星数": 0, "2星数": 0, "3星数": 0, "4星数": 0, "5星数": 10}, "商品信息": {"品牌信息": "克极", "商品名称": "肚子大湿气重】用于脾胃虚弱湿气重引起虚胖肚大脂肪堆积 参苓白术散可搭保济药丸奥利i司他减肥药 3盒装【脾胃虚弱肚子大】", "商品编号": "10082069438797", "店铺": " 洛骆堂旗舰店", "货号": "XY", "药品剂型": "散剂", "类别": "中成药", "适用人群": "通用", "使用方法": "口服", "国产/进口": "国产"}}}, {"index": 47, "title": "艾丽奥利司他胶囊 60mg*6粒 减脂用于肥胖或体重超重患者减肥药OTC国药准字减肥药 1盒装4.粒-塑.效 奥利司他胶囊", "ShopName": "华大中舟大药房旗舰店", "DetailsUrl": "https://item.jd.com/10103171763256.html", "price": "6.50", "imgUrl": null, "统计信息": {"好评数": "1", "好评率": "100%", "差评": "0", "追评数": "0", "总评论数": "1", "评分统计": {"1星数": 0, "2星数": 0, "3星数": 0, "4星数": 0, "5星数": 1}, "商品信息": {"品牌信息": "艾丽", "商品名称": "艾丽奥利司他胶囊 60mg*6粒 减脂用于肥胖或体重超重患者减肥药OTC国药准字减肥药 1盒装4.粒-塑.效 奥利司他胶囊", "商品编号": "10103171763256", "店铺": " 华大中舟大药房旗舰店", "类别": "西药", "适用人群": "成人", "药品剂型": "胶囊剂", "使用方法": "口服", "国产/进口": "国产"}}}, {"index": 48, "title": "爱心东东\n减肥药 强长效期减肥药快减肥瘦肚子减重减脂不反i弹排油塑身减肥成人男女士专用瘦腿瘦肚子 奥利司他胶囊 一盒【四粒建议多盒】", "ShopName": "凰臣堂大药房卖场店", "DetailsUrl": "https://item.jd.com/10098262215864.html", "price": "18.80", "imgUrl": null, "统计信息": {"好评数": "100+", "好评率": "86%", "差评": "10", "追评数": "10+", "总评论数": "500+", "评分统计": {"1星数": 10, "2星数": 4, "3星数": 3, "4星数": 4, "5星数": 100}, "商品信息": {"品牌信息": "雅塑", "商品名称": "减肥药 强长效期减肥药快减肥瘦肚子减重减脂不反i弹排油塑身减肥成人男女士专用瘦腿瘦肚子 奥利司他胶囊 一盒【四粒建议多盒】", "商品编号": "10098262215864", "店铺": " 凰臣堂大药房卖场店", "货号": "001", "适用人群": "成人", "国产/进口": "国产", "药品剂型": "胶囊剂", "类别": "西药", "使用方法": "口服", "适用症状": "腹部胀满"}}}, {"index": 49, "title": "北京同仁堂 轻身消胖丸", "ShopName": "内廷上用中医保健专营店", "DetailsUrl": "https://item.jd.com/10101836574803.html", "price": "122.80", "imgUrl": null, "统计信息": {"好评数": "0", "好评率": "100%", "差评": "0", "追评数": "0", "总评论数": "2", "评分统计": {"1星数": 0, "2星数": 0, "3星数": 0, "4星数": 0, "5星数": 0}, "商品信息": {"品牌信息": "内廷上用", "商品名称": "北京同仁堂 原料轻身消胖丸 减肥降脂 传统工艺 轻身消胖丸颗粒 药食同源 原方配比 内廷上用 买二送一/【3瓶装】基础周期", "商品编号": "10101836574803", "店铺": " 内廷上用中医保健专营店", "类别": "其他", "包装形式": "瓶装", "国产/进口": "国产"}}}, {"index": 50, "title": "效期截止2024年11月】碧生源奥利司他胶囊0.12g/粒用于肥胖和体重超重者的治疗减重排油丸 68粒【60粒*1+8粒*1】", "ShopName": "维康大药房官方旗舰店", "DetailsUrl": "https://item.jd.com/41660447593.html", "price": "315.00", "imgUrl": null, "统计信息": {"好评数": "1.5万+", "好评率": "97%", "差评": "200+", "追评数": "200+", "总评论数": "5万+", "评分统计": {"1星数": 200, "2星数": 55, "3星数": 100, "4星数": 100, "5星数": 10000}, "商品信息": {"品牌信息": "碧生源", "商品名称": "效期截止2024年11月】碧生源奥利司他胶囊0.12g/粒用于肥胖和体重超重者的治疗减重减肥药排油丸 68粒【60粒*1+8粒*1】", "商品编号": "41660447593", "店铺": " 维康大药房官方旗舰店", "药品剂型": "胶囊剂", "适用人群": "通用", "类别": "西药", "使用方法": "口服", "国产/进口": "国产"}}}, {"index": 51, "title": "刘畊宏推荐】瘦大肚腩减赘肉肚子大减肥药治顽固肥胖症药促进脂肪代谢中药减肥 新效期 维生素B1片 【顽固肥胖】3盒疗程装效果明显", "ShopName": "墨如烟大药房旗舰店", "DetailsUrl": "https://item.jd.com/10097680472669.html", "price": "29.28", "imgUrl": null, "统计信息": {"好评数": "10+", "好评率": "100%", "差评": "0", "追评数": "0", "总评论数": "36", "评分统计": {"1星数": 0, "2星数": 0, "3星数": 0, "4星数": 0, "5星数": 15}, "商品信息": {"品牌信息": "玉威", "商品名称": "刘畊宏推荐】瘦大肚腩减赘肉肚子大减肥药治顽固肥胖症药促进脂肪代谢中药减肥 新效期 维生素B1片 【顽固肥胖】3盒疗程装效果明显", "商品编号": "10097680472669", "店铺": " 墨如烟大药房旗舰店", "货号": "kjn", "药品剂型": "片剂", "适用人群": "儿童", "类别": "西药", "使用方法": "口服", "国产/进口": "国产"}}}, {"index": 52, "title": "京东国际\n日本原装进口皇汉堂小粉丸小红丸小药丸便秘丸通便清肠排毒减肥润肠滑肠道排宿便疏通肠道缓解便秘日版 皇汉堂小粉丸100粒【拆盒无包装】", "ShopName": "漱玉医药海外旗舰店", "DetailsUrl": "https://item.jd.com/10098194659088.html", "price": "29.00", "imgUrl": null, "统计信息": {"好评数": "20+", "好评率": "100%", "差评": "0", "追评数": "0", "总评论数": "200+", "评分统计": {"1星数": 0, "2星数": 0, "3星数": 0, "4星数": 0, "5星数": 24}, "商品信息": {"品牌信息": "皇汉堂（KOKANDO）", "商品名称": "日本原装进口皇汉堂小粉丸小红丸小药丸便秘丸通便清肠排毒减肥润肠滑肠道排宿便疏通肠道缓解便秘日版 皇汉堂小粉丸100粒【拆盒无包装】", "商品编号": "10098194659088", "店铺": " 漱玉医药海外旗舰店", "使用方法": "口服", "药品类型": "西药"}}}, {"index": 53, "title": "强效减肥药 治肥胖症强效减肥药中药减肥药减肥瘦肚子燃脂湿气重去湿气排毒大肚子快速复合维生素B片 5盒【顽固肥胖不难瘦】急吃急瘦不反i", "ShopName": "埃拉锶洛阳大药房旗舰店", "DetailsUrl": "https://item.jd.com/10103726659380.html", "price": "49.77", "imgUrl": null, "统计信息": {"好评数": "5", "好评率": "100%", "差评": "0", "追评数": "0", "总评论数": "6", "评分统计": {"1星数": 0, "2星数": 0, "3星数": 0, "4星数": 0, "5星数": 5}, "商品信息": {"品牌信息": "南岛", "商品名称": "强效减肥药 治肥胖症强效减肥药中药减肥药减肥瘦肚子燃脂湿气重去湿气排毒大肚子快速减肥药复合维生素B片 5盒【顽固肥胖不难瘦】急吃急瘦不反i弹", "商品编号": "10103726659380", "店铺": " 埃拉锶洛阳大药房旗舰店", "货号": "CZX", "类别": "西药", "适用症状": "厌食", "适用人群": "通用", "药品剂型": "片剂", "使用方法": "口服", "国产/进口": "国产"}}}, {"index": 54, "title": "减肥药 强效减肥药快顽固性肥胖瘦大肚子脂肪厚治肥胖症去除脂肪代谢不佳健康减脂 维生素B1片 1盒装#多盒效果好", "ShopName": "醉枫染墨大药房旗舰店", "DetailsUrl": "https://item.jd.com/10103756961345.html", "price": "6.80", "imgUrl": null, "统计信息": {"好评数": "10+", "好评率": "100%", "差评": "0", "追评数": "0", "总评论数": "14", "评分统计": {"1星数": 0, "2星数": 0, "3星数": 0, "4星数": 0, "5星数": 11}, "商品信息": {"品牌信息": "玉威", "商品名称": "减肥药 强效减肥药快顽固性肥胖瘦大肚子脂肪厚治肥胖症去除脂肪代谢不佳健康减脂 维生素B1片 1盒装#多盒效果好", "商品编号": "10103756961345", "店铺": " 醉枫染墨大药房旗舰店", "适用人群": "儿童", "类别": "西药", "药品剂型": "片剂", "使用方法": "口服", "国产/进口": "国产"}}}, {"index": 55, "title": "佰纳吉享受压片糖果咀嚼酵素片代餐轻零食 30片", "ShopName": "超前食品专营店", "DetailsUrl": "https://item.jd.com/10029282240781.html", "price": "135.00", "imgUrl": null, "统计信息": {"好评数": "7", "好评率": "100%", "差评": "0", "追评数": "1", "总评论数": "32", "评分统计": {"1星数": 0, "2星数": 0, "3星数": 0, "4星数": 0, "5星数": 7}, "商品信息": {"品牌信息": "佰纳吉（BIO ENERGY）", "商品名称": "佰纳吉享受压片糖果咀嚼酵素片代餐轻零食 30片", "商品编号": "10029282240781", "店铺": " 超前食品专营店", "是否保健食品": "营养膳食补充剂（非食健字）", "类别": "咀嚼片", "剂型": "片剂", "包装形式": "盒装", "国产/进口": "进口"}}}, {"index": 56, "title": "赛乐赛奥利司他胶囊减肥强效减肥药排油正真品国药准字OTC非强效减重药快噢利司他瘦身瘦肚子燃脂通 1盒奥利司他雅/塑 4.颗 男女瘦身减肚子", "ShopName": "黛参苓大药房官方旗舰店", "DetailsUrl": "https://item.jd.com/10102055604104.html", "price": "9.89", "imgUrl": null, "统计信息": {"好评数": "3", "好评率": "75%", "差评": "0", "追评数": "0", "总评论数": "49", "评分统计": {"1星数": 0, "2星数": 1, "3星数": 0, "4星数": 0, "5星数": 3}, "商品信息": {"品牌信息": "赛乐赛", "商品名称": "赛乐赛奥利司他胶囊减肥强效减肥药排油正真品国药准字OTC非强效减重药快噢利司他瘦身瘦肚子燃脂通 1盒奥利司他雅/塑 4.颗 减肥药男女瘦身减肚子", "商品编号": "10102055604104", "店铺": " 黛参苓大药房官方旗舰店", "药品剂型": "胶囊剂", "类别": "西药", "适用人群": "成人", "使用方法": "口服", "国产/进口": "国产"}}}, {"index": 57, "title": "碧生源 奥利司他胶囊减肥药排油丸小蓝盒减重OTC 认准国药准字 1盒25粒【减肥减脂】", "ShopName": "碧生源医药旗舰店", "DetailsUrl": "https://item.jd.com/10047874964651.html", "price": "88.00", "imgUrl": null, "统计信息": {"好评数": "800+", "好评率": "97%", "差评": "10+", "追评数": "7", "总评论数": "5000+", "评分统计": {"1星数": 12, "2星数": 1, "3星数": 7, "4星数": 7, "5星数": 500}, "商品信息": {"品牌信息": "碧生源", "商品名称": "碧生源 奥利司他胶囊减肥药排油丸小蓝盒减重OTC 认准国药准字 1盒25粒【减肥减脂】", "商品编号": "10047874964651", "店铺": " 碧生源医药旗舰店", "货号": "A000220610001", "适用人群": "成人", "药品剂型": "胶囊剂", "类别": "西药，其他", "使用方法": "口服", "国产/进口": "国产"}}}, {"index": 58, "title": "减肥药强效减肥药快奥利司他胶囊排油减肥正真国药准字品男女瘦肚子燃脂瘦身排油减脂暴瘦肥胖大肚子瘦腰瘦腿 一盒装-建议多盒使用", "ShopName": "酸立通SORNADO大药房旗舰店", "DetailsUrl": "https://item.jd.com/10099763668992.html", "price": "8.80", "imgUrl": null, "统计信息": {"好评数": "0", "好评率": "100%", "差评": "0", "追评数": "0", "总评论数": "8", "评分统计": {"1星数": 0, "2星数": 0, "3星数": 0, "4星数": 0, "5星数": 0}, "商品信息": {"品牌信息": "雅塑", "商品名称": "减肥药强效减肥药快奥利司他胶囊排油减肥正真国药准字品男女瘦肚子燃脂瘦身排油减脂暴瘦肥胖大肚子瘦腰瘦腿 一盒装-建议多盒使用", "商品编号": "10099763668992", "店铺": " 酸立通SORNADO大药房旗舰店", "适用人群": "成人", "类别": "西药", "药品剂型": "胶囊剂", "使用方法": "口服", "国产/进口": "国产"}}}, {"index": 59, "title": "爱心东东\n仁和奥利司他胶囊 OTC减肥药 强高效排油减肥抗肥胖 男女瘦腿瘦腰瘦身瘦大肚子 【排油减脂减重】10盒装-共90粒（一月量）", "ShopName": "永春堂大药房旗舰店", "DetailsUrl": "https://item.jd.com/10032025445622.html", "price": "299.00", "imgUrl": null, "统计信息": {"好评数": "2300+", "好评率": "97%", "差评": "30+", "追评数": "10+", "总评论数": "5000+", "评分统计": {"1星数": 34, "2星数": 10, "3星数": 12, "4星数": 15, "5星数": 2000}, "商品信息": {"品牌信息": "仁和", "商品名称": "仁和奥利司他胶囊 OTC减肥药 强高效排油减肥抗肥胖 男女瘦腿瘦腰瘦身瘦大肚子 【排油减脂减重】10盒装-共90粒（一月量）", "商品编号": "10032025445622", "店铺": " 永春堂大药房旗舰店", "适用人群": "成人", "类别": "西药", "药品剂型": "胶囊剂", "使用方法": "口服", "国产/进口": "国产"}}}, {"index": 60, "title": "碧生源 奥利司他胶囊0.12g 减肥减脂减重 排油减肥 1盒共8粒【便携装】", "ShopName": "碧生源大药房旗舰店", "DetailsUrl": "https://item.jd.com/10049689423406.html", "price": "24.00", "imgUrl": null, "统计信息": {"好评数": "50+", "好评率": "94%", "差评": "2", "追评数": "2", "总评论数": "200+", "评分统计": {"1星数": 2, "2星数": 1, "3星数": 0, "4星数": 3, "5星数": 51}, "商品信息": {"品牌信息": "碧生源", "商品名称": "碧生源 奥利司他胶囊0.12g 减肥减脂减重 排油减肥 1盒共8粒【便携装】", "商品编号": "10049689423406", "店铺": " 碧生源大药房旗舰店", "货号": "20994", "适用人群": "成人", "药品剂型": "胶囊剂", "类别": "西药", "使用方法": "口服", "国产/进口": "国产"}}}], "len": 60}